Workbook

Sheet Guide
B1: LEAVE TRACKER TEMPLATE - START HERE
B2: Daily attendance codes become leave balances, payable days and a dashboard. Empty and ready to fill - no employee data inside.
B4: SHEETS
B5: Dashboard | C5: Leave pending and used (CL, SL, PL, Training), department and location tables, monthly attendance snapshot, month-wise table and the OVER-USED / LOW attention list. Only the month cell is typed.
B6: Employee List | C6: Your employees: code, name, designation, department, location, DOJ and exit date (500 rows ready).
B7: Attendance | C7: One row per employee per month with a code in each day cell. Gives payable days, late deduction and leave used.
B8: Leave Record | C8: Automatic CL, SL, PL and Training balances per employee. Only Carry Forward PL is typed.
B9: Settings | C9: Company name, leave year, leave policy numbers and the attendance code legend.
B10: Lists | C10: Dropdown options for Department, Location and Designation.
B12: HOW TO USE
B13: 1. Settings | C13: Type your Company name. Check the leave policy numbers (CL / SL / PL, confirmation days, late-mark rule).
B14: 2. Lists | C14: Replace the example Departments and Locations with your own.
B15: 3. Employee List | C15: Add each employee once. Leave Record fills itself from here.
B16: 4. Leave Record | C16: Enter Carry Forward PL (yellow column) for employees who bring PL from last year.
B17: 5. Attendance | C17: Type Month (1st of month) + Emp Code in the next blank rows, then pick a code in each day cell. Tip: copy last month's Emp Code column and change the month. Grey cells = Sundays / days not in the month.
B18: Check leave | C18: Leave Record updates by itself. Dashboard > Attention list shows OVER-USED / LOW employees.
B19: New leave year | C19: Leave year follows the date automatically (or type it in Settings). Enter carry-forward PL again. Keep old Attendance rows - only the leave year's months are counted.
B21: ATTENDANCE CODES
B22: P / A / HA / L | C22: Present / Absent / Half-day absent (0.5 payable) / Late (payable, counts toward late deduction).
B23: PL / CL / SL / CO | C23: Paid / Casual / Sick leave (1 day deducted from that balance) / Compensatory off.
B24: HPL / HCL | C24: Half-day paid / casual leave: 1 payable day, 0.5 deducted from the balance.
B25: WO / PH / TR | C25: Weekly off / Public holiday / Training day.
B27: COLOUR GUIDE
B28: Yellow cell, blue text | C28: Input cell - type here.
B29: Blue text, white cell | C29: Input column in Employee List / Attendance - type here.
B30: Blue-grey cell | C30: Calculated automatically - do not type over it.
B32: EXAMPLE ENTRY (format only - fictional values, do not copy into the sheets)
B33: Attendance row | C33: Month: 01-Oct-2026 | Emp Code: EMP001 | Day 1 to 31: P P P P P P WO P P P P P P WO ... (one code per day; PH on public holidays)
B35: LIMITS & ASSUMPTIONS
B36: Capacity | C36: Employee List / Leave Record: 500 employees. Attendance: 2,400 employee-months.
B37: Defaults | C37: CL 7, SL 7, PL 18, 90-day confirmation, 3 free late marks, 0.5-day deduction come from your Leave Tracker template. Training days default to 0.

Sheet Dashboard
B1: ="LEAVE & ATTENDANCE DASHBOARD - "&Settings!$C$5 -> LEAVE & ATTENDANCE DASHBOARD - Your Company Name
B2: ="As of "&TEXT(LvAsOf,"dd-mmm-yyyy")&" | Leave year "&LvYear&" | All figures are live from Attendance and Leave Record" -> As of 27-Oct-2026 | Leave year 2026 | All figures are live from Attendance and Leave Record
B4: Active Employees | D4: Exited Employees | F4: CL Pending (days) | H4: SL Pending (days) | J4: PL Pending (days) | L4: Total Leave Pending | N4: Eligible with PL nil
B5: =COUNTIF(M_status,"Active") -> 0 | D5: =COUNTIF(M_status,"Exited") -> 0 | F5: =SUMIFS('Leave Record'!$V$6:$V$505,'Leave Record'!$F$6:$F$505,"Active") -> 0 | H5: =SUMIFS('Leave Record'!$W$6:$W$505,'Leave Record'!$F$6:$F$505,"Active") -> 0 | J5: =SUMIFS('Leave Record'!$X$6:$X$505,'Leave Record'!$F$6:$F$505,"Active") -> 0 | L5: =SUMIFS('Leave Record'!$Z$6:$Z$505,'Leave Record'!$F$6:$F$505,"Active") -> 0 | N5: =COUNTIFS('Leave Record'!$F$6:$F$505,"Active",'Leave Record'!$X$6:$X$505,"<=0",'Leave Record'!$AC$6:$AC$505,"<>NOT ELIGIBLE") -> 0
B7: Employees OVER-USED | D7: Employees LOW balance | F7: Not yet eligible | H7: CL Used (days) | J7: SL Used (days) | L7: PL Used (days) | N7: Training Used (days)
B8: =COUNTIF('Leave Record'!$AC$6:$AC$505,"OVER-USED") -> 0 | D8: =COUNTIF('Leave Record'!$AC$6:$AC$505,"LOW") -> 0 | F8: =COUNTIF('Leave Record'!$AC$6:$AC$505,"NOT ELIGIBLE") -> 0 | H8: =SUMIFS('Leave Record'!$R$6:$R$505,'Leave Record'!$F$6:$F$505,"Active") -> 0 | J8: =SUMIFS('Leave Record'!$S$6:$S$505,'Leave Record'!$F$6:$F$505,"Active") -> 0 | L8: =SUMIFS('Leave Record'!$T$6:$T$505,'Leave Record'!$F$6:$F$505,"Active") -> 0 | N8: =SUMIFS('Leave Record'!$U$6:$U$505,'Leave Record'!$F$6:$F$505,"Active") -> 0
B10: DEPARTMENT-WISE LEAVE (active employees) | J10: LOCATION-WISE LEAVE (active employees)
B11: Department | C11: Active | D11: CL Pending | E11: SL Pending | F11: PL Pending | G11: Total Pending | H11: OVER-USED / LOW | J11: Location | K11: Active | L11: CL Pending | M11: SL Pending | N11: PL Pending | O11: Total Pending
B12: =IF(Lists!A5="","",Lists!A5) -> Admin | C12: =IF($B12="","",COUNTIFS('Leave Record'!$D$6:$D$505,$B12,'Leave Record'!$F$6:$F$505,"Active")) -> 0 | D12: =IF($B12="","",SUMIFS('Leave Record'!$V$6:$V$505,'Leave Record'!$D$6:$D$505,$B12,'Leave Record'!$F$6:$F$505,"Active")) -> 0 | E12: =IF($B12="","",SUMIFS('Leave Record'!$W$6:$W$505,'Leave Record'!$D$6:$D$505,$B12,'Leave Record'!$F$6:$F$505,"Active")) -> 0 | F12: =IF($B12="","",SUMIFS('Leave Record'!$X$6:$X$505,'Leave Record'!$D$6:$D$505,$B12,'Leave Record'!$F$6:$F$505,"Active")) -> 0 | G12: =IF($B12="","",SUMIFS('Leave Record'!$Z$6:$Z$505,'Leave Record'!$D$6:$D$505,$B12,'Leave Record'!$F$6:$F$505,"Active")) -> 0 | H12: =IF($B12="","",COUNTIFS('Leave Record'!$D$6:$D$505,$B12,'Leave Record'!$AC$6:$AC$505,"OVER-USED")+COUNTIFS('Leave Record'!$D$6:$D$505,$B12,'Leave Record'!$AC$6:$AC$505,"LOW")) -> 0 | J12: =IF(Lists!B5="","",Lists!B5) -> Location 1 | K12: =IF($J12="","",COUNTIFS('Leave Record'!$E$6:$E$505,$J12,'Leave Record'!$F$6:$F$505,"Active")) -> 0 | L12: =IF($J12="","",SUMIFS('Leave Record'!$V$6:$V$505,'Leave Record'!$E$6:$E$505,$J12,'Leave Record'!$F$6:$F$505,"Active")) -> 0 | M12: =IF($J12="","",SUMIFS('Leave Record'!$W$6:$W$505,'Leave Record'!$E$6:$E$505,$J12,'Leave Record'!$F$6:$F$505,"Active")) -> 0 | N12: =IF($J12="","",SUMIFS('Leave Record'!$X$6:$X$505,'Leave Record'!$E$6:$E$505,$J12,'Leave Record'!$F$6:$F$505,"Active")) -> 0 | O12: =IF($J12="","",SUMIFS('Leave Record'!$Z$6:$Z$505,'Leave Record'!$E$6:$E$505,$J12,'Leave Record'!$F$6:$F$505,"Active")) -> 0
B13: =IF(Lists!A6="","",Lists!A6) -> Accounts | C13: =IF($B13="","",COUNTIFS('Leave Record'!$D$6:$D$505,$B13,'Leave Record'!$F$6:$F$505,"Active")) -> 0 | D13: =IF($B13="","",SUMIFS('Leave Record'!$V$6:$V$505,'Leave Record'!$D$6:$D$505,$B13,'Leave Record'!$F$6:$F$505,"Active")) -> 0 | E13: =IF($B13="","",SUMIFS('Leave Record'!$W$6:$W$505,'Leave Record'!$D$6:$D$505,$B13,'Leave Record'!$F$6:$F$505,"Active")) -> 0 | F13: =IF($B13="","",SUMIFS('Leave Record'!$X$6:$X$505,'Leave Record'!$D$6:$D$505,$B13,'Leave Record'!$F$6:$F$505,"Active")) -> 0 | G13: =IF($B13="","",SUMIFS('Leave Record'!$Z$6:$Z$505,'Leave Record'!$D$6:$D$505,$B13,'Leave Record'!$F$6:$F$505,"Active")) -> 0 | H13: =IF($B13="","",COUNTIFS('Leave Record'!$D$6:$D$505,$B13,'Leave Record'!$AC$6:$AC$505,"OVER-USED")+COUNTIFS('Leave Record'!$D$6:$D$505,$B13,'Leave Record'!$AC$6:$AC$505,"LOW")) -> 0 | J13: =IF(Lists!B6="","",Lists!B6) -> Location 2 | K13: =IF($J13="","",COUNTIFS('Leave Record'!$E$6:$E$505,$J13,'Leave Record'!$F$6:$F$505,"Active")) -> 0 | L13: =IF($J13="","",SUMIFS('Leave Record'!$V$6:$V$505,'Leave Record'!$E$6:$E$505,$J13,'Leave Record'!$F$6:$F$505,"Active")) -> 0 | M13: =IF($J13="","",SUMIFS('Leave Record'!$W$6:$W$505,'Leave Record'!$E$6:$E$505,$J13,'Leave Record'!$F$6:$F$505,"Active")) -> 0 | N13: =IF($J13="","",SUMIFS('Leave Record'!$X$6:$X$505,'Leave Record'!$E$6:$E$505,$J13,'Leave Record'!$F$6:$F$505,"Active")) -> 0 | O13: =IF($J13="","",SUMIFS('Leave Record'!$Z$6:$Z$505,'Leave Record'!$E$6:$E$505,$J13,'Leave Record'!$F$6:$F$505,"Active")) -> 0
B14: =IF(Lists!A7="","",Lists!A7) -> HR | C14: =IF($B14="","",COUNTIFS('Leave Record'!$D$6:$D$505,$B14,'Leave Record'!$F$6:$F$505,"Active")) -> 0 | D14: =IF($B14="","",SUMIFS('Leave Record'!$V$6:$V$505,'Leave Record'!$D$6:$D$505,$B14,'Leave Record'!$F$6:$F$505,"Active")) -> 0 | E14: =IF($B14="","",SUMIFS('Leave Record'!$W$6:$W$505,'Leave Record'!$D$6:$D$505,$B14,'Leave Record'!$F$6:$F$505,"Active")) -> 0 | F14: =IF($B14="","",SUMIFS('Leave Record'!$X$6:$X$505,'Leave Record'!$D$6:$D$505,$B14,'Leave Record'!$F$6:$F$505,"Active")) -> 0 | G14: =IF($B14="","",SUMIFS('Leave Record'!$Z$6:$Z$505,'Leave Record'!$D$6:$D$505,$B14,'Leave Record'!$F$6:$F$505,"Active")) -> 0 | H14: =IF($B14="","",COUNTIFS('Leave Record'!$D$6:$D$505,$B14,'Leave Record'!$AC$6:$AC$505,"OVER-USED")+COUNTIFS('Leave Record'!$D$6:$D$505,$B14,'Leave Record'!$AC$6:$AC$505,"LOW")) -> 0 | J14: =IF(Lists!B7="","",Lists!B7) | K14: =IF($J14="","",COUNTIFS('Leave Record'!$E$6:$E$505,$J14,'Leave Record'!$F$6:$F$505,"Active")) | L14: =IF($J14="","",SUMIFS('Leave Record'!$V$6:$V$505,'Leave Record'!$E$6:$E$505,$J14,'Leave Record'!$F$6:$F$505,"Active")) | M14: =IF($J14="","",SUMIFS('Leave Record'!$W$6:$W$505,'Leave Record'!$E$6:$E$505,$J14,'Leave Record'!$F$6:$F$505,"Active")) | N14: =IF($J14="","",SUMIFS('Leave Record'!$X$6:$X$505,'Leave Record'!$E$6:$E$505,$J14,'Leave Record'!$F$6:$F$505,"Active")) | O14: =IF($J14="","",SUMIFS('Leave Record'!$Z$6:$Z$505,'Leave Record'!$E$6:$E$505,$J14,'Leave Record'!$F$6:$F$505,"Active"))
B15: =IF(Lists!A8="","",Lists!A8) -> IT | C15: =IF($B15="","",COUNTIFS('Leave Record'!$D$6:$D$505,$B15,'Leave Record'!$F$6:$F$505,"Active")) -> 0 | D15: =IF($B15="","",SUMIFS('Leave Record'!$V$6:$V$505,'Leave Record'!$D$6:$D$505,$B15,'Leave Record'!$F$6:$F$505,"Active")) -> 0 | E15: =IF($B15="","",SUMIFS('Leave Record'!$W$6:$W$505,'Leave Record'!$D$6:$D$505,$B15,'Leave Record'!$F$6:$F$505,"Active")) -> 0 | F15: =IF($B15="","",SUMIFS('Leave Record'!$X$6:$X$505,'Leave Record'!$D$6:$D$505,$B15,'Leave Record'!$F$6:$F$505,"Active")) -> 0 | G15: =IF($B15="","",SUMIFS('Leave Record'!$Z$6:$Z$505,'Leave Record'!$D$6:$D$505,$B15,'Leave Record'!$F$6:$F$505,"Active")) -> 0 | H15: =IF($B15="","",COUNTIFS('Leave Record'!$D$6:$D$505,$B15,'Leave Record'!$AC$6:$AC$505,"OVER-USED")+COUNTIFS('Leave Record'!$D$6:$D$505,$B15,'Leave Record'!$AC$6:$AC$505,"LOW")) -> 0 | J15: =IF(Lists!B8="","",Lists!B8) | K15: =IF($J15="","",COUNTIFS('Leave Record'!$E$6:$E$505,$J15,'Leave Record'!$F$6:$F$505,"Active")) | L15: =IF($J15="","",SUMIFS('Leave Record'!$V$6:$V$505,'Leave Record'!$E$6:$E$505,$J15,'Leave Record'!$F$6:$F$505,"Active")) | M15: =IF($J15="","",SUMIFS('Leave Record'!$W$6:$W$505,'Leave Record'!$E$6:$E$505,$J15,'Leave Record'!$F$6:$F$505,"Active")) | N15: =IF($J15="","",SUMIFS('Leave Record'!$X$6:$X$505,'Leave Record'!$E$6:$E$505,$J15,'Leave Record'!$F$6:$F$505,"Active")) | O15: =IF($J15="","",SUMIFS('Leave Record'!$Z$6:$Z$505,'Leave Record'!$E$6:$E$505,$J15,'Leave Record'!$F$6:$F$505,"Active"))
B16: =IF(Lists!A9="","",Lists!A9) -> Operations | C16: =IF($B16="","",COUNTIFS('Leave Record'!$D$6:$D$505,$B16,'Leave Record'!$F$6:$F$505,"Active")) -> 0 | D16: =IF($B16="","",SUMIFS('Leave Record'!$V$6:$V$505,'Leave Record'!$D$6:$D$505,$B16,'Leave Record'!$F$6:$F$505,"Active")) -> 0 | E16: =IF($B16="","",SUMIFS('Leave Record'!$W$6:$W$505,'Leave Record'!$D$6:$D$505,$B16,'Leave Record'!$F$6:$F$505,"Active")) -> 0 | F16: =IF($B16="","",SUMIFS('Leave Record'!$X$6:$X$505,'Leave Record'!$D$6:$D$505,$B16,'Leave Record'!$F$6:$F$505,"Active")) -> 0 | G16: =IF($B16="","",SUMIFS('Leave Record'!$Z$6:$Z$505,'Leave Record'!$D$6:$D$505,$B16,'Leave Record'!$F$6:$F$505,"Active")) -> 0 | H16: =IF($B16="","",COUNTIFS('Leave Record'!$D$6:$D$505,$B16,'Leave Record'!$AC$6:$AC$505,"OVER-USED")+COUNTIFS('Leave Record'!$D$6:$D$505,$B16,'Leave Record'!$AC$6:$AC$505,"LOW")) -> 0 | J16: =IF(Lists!B9="","",Lists!B9) | K16: =IF($J16="","",COUNTIFS('Leave Record'!$E$6:$E$505,$J16,'Leave Record'!$F$6:$F$505,"Active")) | L16: =IF($J16="","",SUMIFS('Leave Record'!$V$6:$V$505,'Leave Record'!$E$6:$E$505,$J16,'Leave Record'!$F$6:$F$505,"Active")) | M16: =IF($J16="","",SUMIFS('Leave Record'!$W$6:$W$505,'Leave Record'!$E$6:$E$505,$J16,'Leave Record'!$F$6:$F$505,"Active")) | N16: =IF($J16="","",SUMIFS('Leave Record'!$X$6:$X$505,'Leave Record'!$E$6:$E$505,$J16,'Leave Record'!$F$6:$F$505,"Active")) | O16: =IF($J16="","",SUMIFS('Leave Record'!$Z$6:$Z$505,'Leave Record'!$E$6:$E$505,$J16,'Leave Record'!$F$6:$F$505,"Active"))
B17: =IF(Lists!A10="","",Lists!A10) -> Production | C17: =IF($B17="","",COUNTIFS('Leave Record'!$D$6:$D$505,$B17,'Leave Record'!$F$6:$F$505,"Active")) -> 0 | D17: =IF($B17="","",SUMIFS('Leave Record'!$V$6:$V$505,'Leave Record'!$D$6:$D$505,$B17,'Leave Record'!$F$6:$F$505,"Active")) -> 0 | E17: =IF($B17="","",SUMIFS('Leave Record'!$W$6:$W$505,'Leave Record'!$D$6:$D$505,$B17,'Leave Record'!$F$6:$F$505,"Active")) -> 0 | F17: =IF($B17="","",SUMIFS('Leave Record'!$X$6:$X$505,'Leave Record'!$D$6:$D$505,$B17,'Leave Record'!$F$6:$F$505,"Active")) -> 0 | G17: =IF($B17="","",SUMIFS('Leave Record'!$Z$6:$Z$505,'Leave Record'!$D$6:$D$505,$B17,'Leave Record'!$F$6:$F$505,"Active")) -> 0 | H17: =IF($B17="","",COUNTIFS('Leave Record'!$D$6:$D$505,$B17,'Leave Record'!$AC$6:$AC$505,"OVER-USED")+COUNTIFS('Leave Record'!$D$6:$D$505,$B17,'Leave Record'!$AC$6:$AC$505,"LOW")) -> 0 | J17: =IF(Lists!B10="","",Lists!B10) | K17: =IF($J17="","",COUNTIFS('Leave Record'!$E$6:$E$505,$J17,'Leave Record'!$F$6:$F$505,"Active")) | L17: =IF($J17="","",SUMIFS('Leave Record'!$V$6:$V$505,'Leave Record'!$E$6:$E$505,$J17,'Leave Record'!$F$6:$F$505,"Active")) | M17: =IF($J17="","",SUMIFS('Leave Record'!$W$6:$W$505,'Leave Record'!$E$6:$E$505,$J17,'Leave Record'!$F$6:$F$505,"Active")) | N17: =IF($J17="","",SUMIFS('Leave Record'!$X$6:$X$505,'Leave Record'!$E$6:$E$505,$J17,'Leave Record'!$F$6:$F$505,"Active")) | O17: =IF($J17="","",SUMIFS('Leave Record'!$Z$6:$Z$505,'Leave Record'!$E$6:$E$505,$J17,'Leave Record'!$F$6:$F$505,"Active"))
B18: =IF(Lists!A11="","",Lists!A11) -> Sales | C18: =IF($B18="","",COUNTIFS('Leave Record'!$D$6:$D$505,$B18,'Leave Record'!$F$6:$F$505,"Active")) -> 0 | D18: =IF($B18="","",SUMIFS('Leave Record'!$V$6:$V$505,'Leave Record'!$D$6:$D$505,$B18,'Leave Record'!$F$6:$F$505,"Active")) -> 0 | E18: =IF($B18="","",SUMIFS('Leave Record'!$W$6:$W$505,'Leave Record'!$D$6:$D$505,$B18,'Leave Record'!$F$6:$F$505,"Active")) -> 0 | F18: =IF($B18="","",SUMIFS('Leave Record'!$X$6:$X$505,'Leave Record'!$D$6:$D$505,$B18,'Leave Record'!$F$6:$F$505,"Active")) -> 0 | G18: =IF($B18="","",SUMIFS('Leave Record'!$Z$6:$Z$505,'Leave Record'!$D$6:$D$505,$B18,'Leave Record'!$F$6:$F$505,"Active")) -> 0 | H18: =IF($B18="","",COUNTIFS('Leave Record'!$D$6:$D$505,$B18,'Leave Record'!$AC$6:$AC$505,"OVER-USED")+COUNTIFS('Leave Record'!$D$6:$D$505,$B18,'Leave Record'!$AC$6:$AC$505,"LOW")) -> 0 | J18: =IF(Lists!B11="","",Lists!B11) | K18: =IF($J18="","",COUNTIFS('Leave Record'!$E$6:$E$505,$J18,'Leave Record'!$F$6:$F$505,"Active")) | L18: =IF($J18="","",SUMIFS('Leave Record'!$V$6:$V$505,'Leave Record'!$E$6:$E$505,$J18,'Leave Record'!$F$6:$F$505,"Active")) | M18: =IF($J18="","",SUMIFS('Leave Record'!$W$6:$W$505,'Leave Record'!$E$6:$E$505,$J18,'Leave Record'!$F$6:$F$505,"Active")) | N18: =IF($J18="","",SUMIFS('Leave Record'!$X$6:$X$505,'Leave Record'!$E$6:$E$505,$J18,'Leave Record'!$F$6:$F$505,"Active")) | O18: =IF($J18="","",SUMIFS('Leave Record'!$Z$6:$Z$505,'Leave Record'!$E$6:$E$505,$J18,'Leave Record'!$F$6:$F$505,"Active"))
B19: =IF(Lists!A12="","",Lists!A12) -> Stores | C19: =IF($B19="","",COUNTIFS('Leave Record'!$D$6:$D$505,$B19,'Leave Record'!$F$6:$F$505,"Active")) -> 0 | D19: =IF($B19="","",SUMIFS('Leave Record'!$V$6:$V$505,'Leave Record'!$D$6:$D$505,$B19,'Leave Record'!$F$6:$F$505,"Active")) -> 0 | E19: =IF($B19="","",SUMIFS('Leave Record'!$W$6:$W$505,'Leave Record'!$D$6:$D$505,$B19,'Leave Record'!$F$6:$F$505,"Active")) -> 0 | F19: =IF($B19="","",SUMIFS('Leave Record'!$X$6:$X$505,'Leave Record'!$D$6:$D$505,$B19,'Leave Record'!$F$6:$F$505,"Active")) -> 0 | G19: =IF($B19="","",SUMIFS('Leave Record'!$Z$6:$Z$505,'Leave Record'!$D$6:$D$505,$B19,'Leave Record'!$F$6:$F$505,"Active")) -> 0 | H19: =IF($B19="","",COUNTIFS('Leave Record'!$D$6:$D$505,$B19,'Leave Record'!$AC$6:$AC$505,"OVER-USED")+COUNTIFS('Leave Record'!$D$6:$D$505,$B19,'Leave Record'!$AC$6:$AC$505,"LOW")) -> 0 | J19: =IF(Lists!B12="","",Lists!B12) | K19: =IF($J19="","",COUNTIFS('Leave Record'!$E$6:$E$505,$J19,'Leave Record'!$F$6:$F$505,"Active")) | L19: =IF($J19="","",SUMIFS('Leave Record'!$V$6:$V$505,'Leave Record'!$E$6:$E$505,$J19,'Leave Record'!$F$6:$F$505,"Active")) | M19: =IF($J19="","",SUMIFS('Leave Record'!$W$6:$W$505,'Leave Record'!$E$6:$E$505,$J19,'Leave Record'!$F$6:$F$505,"Active")) | N19: =IF($J19="","",SUMIFS('Leave Record'!$X$6:$X$505,'Leave Record'!$E$6:$E$505,$J19,'Leave Record'!$F$6:$F$505,"Active")) | O19: =IF($J19="","",SUMIFS('Leave Record'!$Z$6:$Z$505,'Leave Record'!$E$6:$E$505,$J19,'Leave Record'!$F$6:$F$505,"Active"))
B20: =IF(Lists!A13="","",Lists!A13) | C20: =IF($B20="","",COUNTIFS('Leave Record'!$D$6:$D$505,$B20,'Leave Record'!$F$6:$F$505,"Active")) | D20: =IF($B20="","",SUMIFS('Leave Record'!$V$6:$V$505,'Leave Record'!$D$6:$D$505,$B20,'Leave Record'!$F$6:$F$505,"Active")) | E20: =IF($B20="","",SUMIFS('Leave Record'!$W$6:$W$505,'Leave Record'!$D$6:$D$505,$B20,'Leave Record'!$F$6:$F$505,"Active")) | F20: =IF($B20="","",SUMIFS('Leave Record'!$X$6:$X$505,'Leave Record'!$D$6:$D$505,$B20,'Leave Record'!$F$6:$F$505,"Active")) | G20: =IF($B20="","",SUMIFS('Leave Record'!$Z$6:$Z$505,'Leave Record'!$D$6:$D$505,$B20,'Leave Record'!$F$6:$F$505,"Active")) | H20: =IF($B20="","",COUNTIFS('Leave Record'!$D$6:$D$505,$B20,'Leave Record'!$AC$6:$AC$505,"OVER-USED")+COUNTIFS('Leave Record'!$D$6:$D$505,$B20,'Leave Record'!$AC$6:$AC$505,"LOW")) | J20: =IF(Lists!B13="","",Lists!B13) | K20: =IF($J20="","",COUNTIFS('Leave Record'!$E$6:$E$505,$J20,'Leave Record'!$F$6:$F$505,"Active")) | L20: =IF($J20="","",SUMIFS('Leave Record'!$V$6:$V$505,'Leave Record'!$E$6:$E$505,$J20,'Leave Record'!$F$6:$F$505,"Active")) | M20: =IF($J20="","",SUMIFS('Leave Record'!$W$6:$W$505,'Leave Record'!$E$6:$E$505,$J20,'Leave Record'!$F$6:$F$505,"Active")) | N20: =IF($J20="","",SUMIFS('Leave Record'!$X$6:$X$505,'Leave Record'!$E$6:$E$505,$J20,'Leave Record'!$F$6:$F$505,"Active")) | O20: =IF($J20="","",SUMIFS('Leave Record'!$Z$6:$Z$505,'Leave Record'!$E$6:$E$505,$J20,'Leave Record'!$F$6:$F$505,"Active"))
B21: =IF(Lists!A14="","",Lists!A14) | C21: =IF($B21="","",COUNTIFS('Leave Record'!$D$6:$D$505,$B21,'Leave Record'!$F$6:$F$505,"Active")) | D21: =IF($B21="","",SUMIFS('Leave Record'!$V$6:$V$505,'Leave Record'!$D$6:$D$505,$B21,'Leave Record'!$F$6:$F$505,"Active")) | E21: =IF($B21="","",SUMIFS('Leave Record'!$W$6:$W$505,'Leave Record'!$D$6:$D$505,$B21,'Leave Record'!$F$6:$F$505,"Active")) | F21: =IF($B21="","",SUMIFS('Leave Record'!$X$6:$X$505,'Leave Record'!$D$6:$D$505,$B21,'Leave Record'!$F$6:$F$505,"Active")) | G21: =IF($B21="","",SUMIFS('Leave Record'!$Z$6:$Z$505,'Leave Record'!$D$6:$D$505,$B21,'Leave Record'!$F$6:$F$505,"Active")) | H21: =IF($B21="","",COUNTIFS('Leave Record'!$D$6:$D$505,$B21,'Leave Record'!$AC$6:$AC$505,"OVER-USED")+COUNTIFS('Leave Record'!$D$6:$D$505,$B21,'Leave Record'!$AC$6:$AC$505,"LOW")) | J21: =IF(Lists!B14="","",Lists!B14) | K21: =IF($J21="","",COUNTIFS('Leave Record'!$E$6:$E$505,$J21,'Leave Record'!$F$6:$F$505,"Active")) | L21: =IF($J21="","",SUMIFS('Leave Record'!$V$6:$V$505,'Leave Record'!$E$6:$E$505,$J21,'Leave Record'!$F$6:$F$505,"Active")) | M21: =IF($J21="","",SUMIFS('Leave Record'!$W$6:$W$505,'Leave Record'!$E$6:$E$505,$J21,'Leave Record'!$F$6:$F$505,"Active")) | N21: =IF($J21="","",SUMIFS('Leave Record'!$X$6:$X$505,'Leave Record'!$E$6:$E$505,$J21,'Leave Record'!$F$6:$F$505,"Active")) | O21: =IF($J21="","",SUMIFS('Leave Record'!$Z$6:$Z$505,'Leave Record'!$E$6:$E$505,$J21,'Leave Record'!$F$6:$F$505,"Active"))
B22: =IF(Lists!A15="","",Lists!A15) | C22: =IF($B22="","",COUNTIFS('Leave Record'!$D$6:$D$505,$B22,'Leave Record'!$F$6:$F$505,"Active")) | D22: =IF($B22="","",SUMIFS('Leave Record'!$V$6:$V$505,'Leave Record'!$D$6:$D$505,$B22,'Leave Record'!$F$6:$F$505,"Active")) | E22: =IF($B22="","",SUMIFS('Leave Record'!$W$6:$W$505,'Leave Record'!$D$6:$D$505,$B22,'Leave Record'!$F$6:$F$505,"Active")) | F22: =IF($B22="","",SUMIFS('Leave Record'!$X$6:$X$505,'Leave Record'!$D$6:$D$505,$B22,'Leave Record'!$F$6:$F$505,"Active")) | G22: =IF($B22="","",SUMIFS('Leave Record'!$Z$6:$Z$505,'Leave Record'!$D$6:$D$505,$B22,'Leave Record'!$F$6:$F$505,"Active")) | H22: =IF($B22="","",COUNTIFS('Leave Record'!$D$6:$D$505,$B22,'Leave Record'!$AC$6:$AC$505,"OVER-USED")+COUNTIFS('Leave Record'!$D$6:$D$505,$B22,'Leave Record'!$AC$6:$AC$505,"LOW")) | J22: TOTAL | K22: =SUM(K12:K21) -> 0 | L22: =SUM(L12:L21) -> 0 | M22: =SUM(M12:M21) -> 0 | N22: =SUM(N12:N21) -> 0 | O22: =SUM(O12:O21) -> 0
B23: =IF(Lists!A16="","",Lists!A16) | C23: =IF($B23="","",COUNTIFS('Leave Record'!$D$6:$D$505,$B23,'Leave Record'!$F$6:$F$505,"Active")) | D23: =IF($B23="","",SUMIFS('Leave Record'!$V$6:$V$505,'Leave Record'!$D$6:$D$505,$B23,'Leave Record'!$F$6:$F$505,"Active")) | E23: =IF($B23="","",SUMIFS('Leave Record'!$W$6:$W$505,'Leave Record'!$D$6:$D$505,$B23,'Leave Record'!$F$6:$F$505,"Active")) | F23: =IF($B23="","",SUMIFS('Leave Record'!$X$6:$X$505,'Leave Record'!$D$6:$D$505,$B23,'Leave Record'!$F$6:$F$505,"Active")) | G23: =IF($B23="","",SUMIFS('Leave Record'!$Z$6:$Z$505,'Leave Record'!$D$6:$D$505,$B23,'Leave Record'!$F$6:$F$505,"Active")) | H23: =IF($B23="","",COUNTIFS('Leave Record'!$D$6:$D$505,$B23,'Leave Record'!$AC$6:$AC$505,"OVER-USED")+COUNTIFS('Leave Record'!$D$6:$D$505,$B23,'Leave Record'!$AC$6:$AC$505,"LOW")) | J23: ="Active employees with no / unlisted location: "&(B5-K22) -> Active employees with no / unlisted location: 0
B24: TOTAL | C24: =SUM(C12:C23) -> 0 | D24: =SUM(D12:D23) -> 0 | E24: =SUM(E12:E23) -> 0 | F24: =SUM(F12:F23) -> 0 | G24: =SUM(G12:G23) -> 0 | H24: =SUM(H12:H23) -> 0
B25: ="Active employees with no / unlisted department: "&(B5-C24) -> Active employees with no / unlisted department: 0
B27: ATTENDANCE SNAPSHOT
B28: Month (type 1st of month) | C28: =DATE(YEAR(LvAsOf),MONTH(LvAsOf),1) -> 46296 | D28: Default = current month. Type a date to view another month.
B29: Employees marked | D29: Present days | F29: Absent days | H29: Late marks | J29: Leave days taken (CL+SL+PL) | L29: Net payable days | N29: Unmarked days
B30: =COUNTIFS(Attendance!$A$6:$A$2405,">="&$C$28,Attendance!$A$6:$A$2405,"<="&EOMONTH($C$28,0),Attendance!$B$6:$B$2405,"<>") -> 0 | D30: =SUMIFS(Attendance!$AK$6:$AK$2405,Attendance!$A$6:$A$2405,">="&$C$28,Attendance!$A$6:$A$2405,"<="&EOMONTH($C$28,0)) -> 0 | F30: =SUMIFS(Attendance!$AL$6:$AL$2405,Attendance!$A$6:$A$2405,">="&$C$28,Attendance!$A$6:$A$2405,"<="&EOMONTH($C$28,0)) -> 0 | H30: =SUMIFS(Attendance!$AN$6:$AN$2405,Attendance!$A$6:$A$2405,">="&$C$28,Attendance!$A$6:$A$2405,"<="&EOMONTH($C$28,0)) -> 0 | J30: =SUMIFS(Attendance!$AX$6:$AX$2405,Attendance!$A$6:$A$2405,">="&$C$28,Attendance!$A$6:$A$2405,"<="&EOMONTH($C$28,0))+SUMIFS(Attendance!$AY$6:$AY$2405,Attendance!$A$6:$A$2405,">="&$C$28,Attendance!$A$6:$A$2405,"<="&EOMONTH($C$28,0))+SUMIFS(Attendance!$AZ$6:$AZ$2405,Attendance!$A$6:$A$2405,">="&$C$28,Attendance!$A$6:$A$2405,"<="&EOMONTH($C$28,0)) -> 0 | L30: =SUMIFS(Attendance!$BC$6:$BC$2405,Attendance!$A$6:$A$2405,">="&$C$28,Attendance!$A$6:$A$2405,"<="&EOMONTH($C$28,0)) -> 0 | N30: =SUMIFS(Attendance!$BD$6:$BD$2405,Attendance!$A$6:$A$2405,">="&$C$28,Attendance!$A$6:$A$2405,"<="&EOMONTH($C$28,0)) -> 0
B33: ATTENTION LIST - employees OVER-USED or LOW on leave (first 10; filter Status Flag in Leave Record for all)
B34: Code | C34: Employee | E34: Department | F34: CL | G34: SL | H34: PL | I34: Training | J34: Total Pending | K34: Status
B35: =IFERROR(INDEX('Leave Record'!$A$6:$A$505,MATCH(ROWS(B$35:B35),'Leave Record'!$AD$6:$AD$505,0)),"") | C35: =IFERROR(INDEX('Leave Record'!$B$6:$B$505,MATCH(ROWS(B$35:B35),'Leave Record'!$AD$6:$AD$505,0)),"") | E35: =IFERROR(INDEX('Leave Record'!$D$6:$D$505,MATCH(ROWS(B$35:B35),'Leave Record'!$AD$6:$AD$505,0)),"") | F35: =IFERROR(INDEX('Leave Record'!$V$6:$V$505,MATCH(ROWS(B$35:B35),'Leave Record'!$AD$6:$AD$505,0)),"") | G35: =IFERROR(INDEX('Leave Record'!$W$6:$W$505,MATCH(ROWS(B$35:B35),'Leave Record'!$AD$6:$AD$505,0)),"") | H35: =IFERROR(INDEX('Leave Record'!$X$6:$X$505,MATCH(ROWS(B$35:B35),'Leave Record'!$AD$6:$AD$505,0)),"") | I35: =IFERROR(INDEX('Leave Record'!$Y$6:$Y$505,MATCH(ROWS(B$35:B35),'Leave Record'!$AD$6:$AD$505,0)),"") | J35: =IFERROR(INDEX('Leave Record'!$Z$6:$Z$505,MATCH(ROWS(B$35:B35),'Leave Record'!$AD$6:$AD$505,0)),"") | K35: =IFERROR(INDEX('Leave Record'!$AC$6:$AC$505,MATCH(ROWS(B$35:B35),'Leave Record'!$AD$6:$AD$505,0)),"")
B36: =IFERROR(INDEX('Leave Record'!$A$6:$A$505,MATCH(ROWS(B$35:B36),'Leave Record'!$AD$6:$AD$505,0)),"") | C36: =IFERROR(INDEX('Leave Record'!$B$6:$B$505,MATCH(ROWS(B$35:B36),'Leave Record'!$AD$6:$AD$505,0)),"") | E36: =IFERROR(INDEX('Leave Record'!$D$6:$D$505,MATCH(ROWS(B$35:B36),'Leave Record'!$AD$6:$AD$505,0)),"") | F36: =IFERROR(INDEX('Leave Record'!$V$6:$V$505,MATCH(ROWS(B$35:B36),'Leave Record'!$AD$6:$AD$505,0)),"") | G36: =IFERROR(INDEX('Leave Record'!$W$6:$W$505,MATCH(ROWS(B$35:B36),'Leave Record'!$AD$6:$AD$505,0)),"") | H36: =IFERROR(INDEX('Leave Record'!$X$6:$X$505,MATCH(ROWS(B$35:B36),'Leave Record'!$AD$6:$AD$505,0)),"") | I36: =IFERROR(INDEX('Leave Record'!$Y$6:$Y$505,MATCH(ROWS(B$35:B36),'Leave Record'!$AD$6:$AD$505,0)),"") | J36: =IFERROR(INDEX('Leave Record'!$Z$6:$Z$505,MATCH(ROWS(B$35:B36),'Leave Record'!$AD$6:$AD$505,0)),"") | K36: =IFERROR(INDEX('Leave Record'!$AC$6:$AC$505,MATCH(ROWS(B$35:B36),'Leave Record'!$AD$6:$AD$505,0)),"")
B37: =IFERROR(INDEX('Leave Record'!$A$6:$A$505,MATCH(ROWS(B$35:B37),'Leave Record'!$AD$6:$AD$505,0)),"") | C37: =IFERROR(INDEX('Leave Record'!$B$6:$B$505,MATCH(ROWS(B$35:B37),'Leave Record'!$AD$6:$AD$505,0)),"") | E37: =IFERROR(INDEX('Leave Record'!$D$6:$D$505,MATCH(ROWS(B$35:B37),'Leave Record'!$AD$6:$AD$505,0)),"") | F37: =IFERROR(INDEX('Leave Record'!$V$6:$V$505,MATCH(ROWS(B$35:B37),'Leave Record'!$AD$6:$AD$505,0)),"") | G37: =IFERROR(INDEX('Leave Record'!$W$6:$W$505,MATCH(ROWS(B$35:B37),'Leave Record'!$AD$6:$AD$505,0)),"") | H37: =IFERROR(INDEX('Leave Record'!$X$6:$X$505,MATCH(ROWS(B$35:B37),'Leave Record'!$AD$6:$AD$505,0)),"") | I37: =IFERROR(INDEX('Leave Record'!$Y$6:$Y$505,MATCH(ROWS(B$35:B37),'Leave Record'!$AD$6:$AD$505,0)),"") | J37: =IFERROR(INDEX('Leave Record'!$Z$6:$Z$505,MATCH(ROWS(B$35:B37),'Leave Record'!$AD$6:$AD$505,0)),"") | K37: =IFERROR(INDEX('Leave Record'!$AC$6:$AC$505,MATCH(ROWS(B$35:B37),'Leave Record'!$AD$6:$AD$505,0)),"")
B38: =IFERROR(INDEX('Leave Record'!$A$6:$A$505,MATCH(ROWS(B$35:B38),'Leave Record'!$AD$6:$AD$505,0)),"") | C38: =IFERROR(INDEX('Leave Record'!$B$6:$B$505,MATCH(ROWS(B$35:B38),'Leave Record'!$AD$6:$AD$505,0)),"") | E38: =IFERROR(INDEX('Leave Record'!$D$6:$D$505,MATCH(ROWS(B$35:B38),'Leave Record'!$AD$6:$AD$505,0)),"") | F38: =IFERROR(INDEX('Leave Record'!$V$6:$V$505,MATCH(ROWS(B$35:B38),'Leave Record'!$AD$6:$AD$505,0)),"") | G38: =IFERROR(INDEX('Leave Record'!$W$6:$W$505,MATCH(ROWS(B$35:B38),'Leave Record'!$AD$6:$AD$505,0)),"") | H38: =IFERROR(INDEX('Leave Record'!$X$6:$X$505,MATCH(ROWS(B$35:B38),'Leave Record'!$AD$6:$AD$505,0)),"") | I38: =IFERROR(INDEX('Leave Record'!$Y$6:$Y$505,MATCH(ROWS(B$35:B38),'Leave Record'!$AD$6:$AD$505,0)),"") | J38: =IFERROR(INDEX('Leave Record'!$Z$6:$Z$505,MATCH(ROWS(B$35:B38),'Leave Record'!$AD$6:$AD$505,0)),"") | K38: =IFERROR(INDEX('Leave Record'!$AC$6:$AC$505,MATCH(ROWS(B$35:B38),'Leave Record'!$AD$6:$AD$505,0)),"")
B39: =IFERROR(INDEX('Leave Record'!$A$6:$A$505,MATCH(ROWS(B$35:B39),'Leave Record'!$AD$6:$AD$505,0)),"") | C39: =IFERROR(INDEX('Leave Record'!$B$6:$B$505,MATCH(ROWS(B$35:B39),'Leave Record'!$AD$6:$AD$505,0)),"") | E39: =IFERROR(INDEX('Leave Record'!$D$6:$D$505,MATCH(ROWS(B$35:B39),'Leave Record'!$AD$6:$AD$505,0)),"") | F39: =IFERROR(INDEX('Leave Record'!$V$6:$V$505,MATCH(ROWS(B$35:B39),'Leave Record'!$AD$6:$AD$505,0)),"") | G39: =IFERROR(INDEX('Leave Record'!$W$6:$W$505,MATCH(ROWS(B$35:B39),'Leave Record'!$AD$6:$AD$505,0)),"") | H39: =IFERROR(INDEX('Leave Record'!$X$6:$X$505,MATCH(ROWS(B$35:B39),'Leave Record'!$AD$6:$AD$505,0)),"") | I39: =IFERROR(INDEX('Leave Record'!$Y$6:$Y$505,MATCH(ROWS(B$35:B39),'Leave Record'!$AD$6:$AD$505,0)),"") | J39: =IFERROR(INDEX('Leave Record'!$Z$6:$Z$505,MATCH(ROWS(B$35:B39),'Leave Record'!$AD$6:$AD$505,0)),"") | K39: =IFERROR(INDEX('Leave Record'!$AC$6:$AC$505,MATCH(ROWS(B$35:B39),'Leave Record'!$AD$6:$AD$505,0)),"")
B40: =IFERROR(INDEX('Leave Record'!$A$6:$A$505,MATCH(ROWS(B$35:B40),'Leave Record'!$AD$6:$AD$505,0)),"") | C40: =IFERROR(INDEX('Leave Record'!$B$6:$B$505,MATCH(ROWS(B$35:B40),'Leave Record'!$AD$6:$AD$505,0)),"") | E40: =IFERROR(INDEX('Leave Record'!$D$6:$D$505,MATCH(ROWS(B$35:B40),'Leave Record'!$AD$6:$AD$505,0)),"") | F40: =IFERROR(INDEX('Leave Record'!$V$6:$V$505,MATCH(ROWS(B$35:B40),'Leave Record'!$AD$6:$AD$505,0)),"") | G40: =IFERROR(INDEX('Leave Record'!$W$6:$W$505,MATCH(ROWS(B$35:B40),'Leave Record'!$AD$6:$AD$505,0)),"") | H40: =IFERROR(INDEX('Leave Record'!$X$6:$X$505,MATCH(ROWS(B$35:B40),'Leave Record'!$AD$6:$AD$505,0)),"") | I40: =IFERROR(INDEX('Leave Record'!$Y$6:$Y$505,MATCH(ROWS(B$35:B40),'Leave Record'!$AD$6:$AD$505,0)),"") | J40: =IFERROR(INDEX('Leave Record'!$Z$6:$Z$505,MATCH(ROWS(B$35:B40),'Leave Record'!$AD$6:$AD$505,0)),"") | K40: =IFERROR(INDEX('Leave Record'!$AC$6:$AC$505,MATCH(ROWS(B$35:B40),'Leave Record'!$AD$6:$AD$505,0)),"")
B41: =IFERROR(INDEX('Leave Record'!$A$6:$A$505,MATCH(ROWS(B$35:B41),'Leave Record'!$AD$6:$AD$505,0)),"") | C41: =IFERROR(INDEX('Leave Record'!$B$6:$B$505,MATCH(ROWS(B$35:B41),'Leave Record'!$AD$6:$AD$505,0)),"") | E41: =IFERROR(INDEX('Leave Record'!$D$6:$D$505,MATCH(ROWS(B$35:B41),'Leave Record'!$AD$6:$AD$505,0)),"") | F41: =IFERROR(INDEX('Leave Record'!$V$6:$V$505,MATCH(ROWS(B$35:B41),'Leave Record'!$AD$6:$AD$505,0)),"") | G41: =IFERROR(INDEX('Leave Record'!$W$6:$W$505,MATCH(ROWS(B$35:B41),'Leave Record'!$AD$6:$AD$505,0)),"") | H41: =IFERROR(INDEX('Leave Record'!$X$6:$X$505,MATCH(ROWS(B$35:B41),'Leave Record'!$AD$6:$AD$505,0)),"") | I41: =IFERROR(INDEX('Leave Record'!$Y$6:$Y$505,MATCH(ROWS(B$35:B41),'Leave Record'!$AD$6:$AD$505,0)),"") | J41: =IFERROR(INDEX('Leave Record'!$Z$6:$Z$505,MATCH(ROWS(B$35:B41),'Leave Record'!$AD$6:$AD$505,0)),"") | K41: =IFERROR(INDEX('Leave Record'!$AC$6:$AC$505,MATCH(ROWS(B$35:B41),'Leave Record'!$AD$6:$AD$505,0)),"")
B42: =IFERROR(INDEX('Leave Record'!$A$6:$A$505,MATCH(ROWS(B$35:B42),'Leave Record'!$AD$6:$AD$505,0)),"") | C42: =IFERROR(INDEX('Leave Record'!$B$6:$B$505,MATCH(ROWS(B$35:B42),'Leave Record'!$AD$6:$AD$505,0)),"") | E42: =IFERROR(INDEX('Leave Record'!$D$6:$D$505,MATCH(ROWS(B$35:B42),'Leave Record'!$AD$6:$AD$505,0)),"") | F42: =IFERROR(INDEX('Leave Record'!$V$6:$V$505,MATCH(ROWS(B$35:B42),'Leave Record'!$AD$6:$AD$505,0)),"") | G42: =IFERROR(INDEX('Leave Record'!$W$6:$W$505,MATCH(ROWS(B$35:B42),'Leave Record'!$AD$6:$AD$505,0)),"") | H42: =IFERROR(INDEX('Leave Record'!$X$6:$X$505,MATCH(ROWS(B$35:B42),'Leave Record'!$AD$6:$AD$505,0)),"") | I42: =IFERROR(INDEX('Leave Record'!$Y$6:$Y$505,MATCH(ROWS(B$35:B42),'Leave Record'!$AD$6:$AD$505,0)),"") | J42: =IFERROR(INDEX('Leave Record'!$Z$6:$Z$505,MATCH(ROWS(B$35:B42),'Leave Record'!$AD$6:$AD$505,0)),"") | K42: =IFERROR(INDEX('Leave Record'!$AC$6:$AC$505,MATCH(ROWS(B$35:B42),'Leave Record'!$AD$6:$AD$505,0)),"")
B43: =IFERROR(INDEX('Leave Record'!$A$6:$A$505,MATCH(ROWS(B$35:B43),'Leave Record'!$AD$6:$AD$505,0)),"") | C43: =IFERROR(INDEX('Leave Record'!$B$6:$B$505,MATCH(ROWS(B$35:B43),'Leave Record'!$AD$6:$AD$505,0)),"") | E43: =IFERROR(INDEX('Leave Record'!$D$6:$D$505,MATCH(ROWS(B$35:B43),'Leave Record'!$AD$6:$AD$505,0)),"") | F43: =IFERROR(INDEX('Leave Record'!$V$6:$V$505,MATCH(ROWS(B$35:B43),'Leave Record'!$AD$6:$AD$505,0)),"") | G43: =IFERROR(INDEX('Leave Record'!$W$6:$W$505,MATCH(ROWS(B$35:B43),'Leave Record'!$AD$6:$AD$505,0)),"") | H43: =IFERROR(INDEX('Leave Record'!$X$6:$X$505,MATCH(ROWS(B$35:B43),'Leave Record'!$AD$6:$AD$505,0)),"") | I43: =IFERROR(INDEX('Leave Record'!$Y$6:$Y$505,MATCH(ROWS(B$35:B43),'Leave Record'!$AD$6:$AD$505,0)),"") | J43: =IFERROR(INDEX('Leave Record'!$Z$6:$Z$505,MATCH(ROWS(B$35:B43),'Leave Record'!$AD$6:$AD$505,0)),"") | K43: =IFERROR(INDEX('Leave Record'!$AC$6:$AC$505,MATCH(ROWS(B$35:B43),'Leave Record'!$AD$6:$AD$505,0)),"")
B44: =IFERROR(INDEX('Leave Record'!$A$6:$A$505,MATCH(ROWS(B$35:B44),'Leave Record'!$AD$6:$AD$505,0)),"") | C44: =IFERROR(INDEX('Leave Record'!$B$6:$B$505,MATCH(ROWS(B$35:B44),'Leave Record'!$AD$6:$AD$505,0)),"") | E44: =IFERROR(INDEX('Leave Record'!$D$6:$D$505,MATCH(ROWS(B$35:B44),'Leave Record'!$AD$6:$AD$505,0)),"") | F44: =IFERROR(INDEX('Leave Record'!$V$6:$V$505,MATCH(ROWS(B$35:B44),'Leave Record'!$AD$6:$AD$505,0)),"") | G44: =IFERROR(INDEX('Leave Record'!$W$6:$W$505,MATCH(ROWS(B$35:B44),'Leave Record'!$AD$6:$AD$505,0)),"") | H44: =IFERROR(INDEX('Leave Record'!$X$6:$X$505,MATCH(ROWS(B$35:B44),'Leave Record'!$AD$6:$AD$505,0)),"") | I44: =IFERROR(INDEX('Leave Record'!$Y$6:$Y$505,MATCH(ROWS(B$35:B44),'Leave Record'!$AD$6:$AD$505,0)),"") | J44: =IFERROR(INDEX('Leave Record'!$Z$6:$Z$505,MATCH(ROWS(B$35:B44),'Leave Record'!$AD$6:$AD$505,0)),"") | K44: =IFERROR(INDEX('Leave Record'!$AC$6:$AC$505,MATCH(ROWS(B$35:B44),'Leave Record'!$AD$6:$AD$505,0)),"")
B47: ="MONTH-WISE ATTENDANCE - leave year "&LvYear -> MONTH-WISE ATTENDANCE - leave year 2026
B48: Month | C48: Employees marked | D48: Present days | E48: Absent days | F48: Late marks | G48: Leave days (CL+SL+PL) | H48: Net payable days
B49: =DATE(LvYear,1,1) -> 46023 | C49: =COUNTIFS(Attendance!$A$6:$A$2405,">="&$B49,Attendance!$A$6:$A$2405,"<="&EOMONTH($B49,0),Attendance!$B$6:$B$2405,"<>") -> 0 | D49: =SUMIFS(Attendance!$AK$6:$AK$2405,Attendance!$A$6:$A$2405,">="&$B49,Attendance!$A$6:$A$2405,"<="&EOMONTH($B49,0)) -> 0 | E49: =SUMIFS(Attendance!$AL$6:$AL$2405,Attendance!$A$6:$A$2405,">="&$B49,Attendance!$A$6:$A$2405,"<="&EOMONTH($B49,0)) -> 0 | F49: =SUMIFS(Attendance!$AN$6:$AN$2405,Attendance!$A$6:$A$2405,">="&$B49,Attendance!$A$6:$A$2405,"<="&EOMONTH($B49,0)) -> 0 | G49: =SUMIFS(Attendance!$AX$6:$AX$2405,Attendance!$A$6:$A$2405,">="&$B49,Attendance!$A$6:$A$2405,"<="&EOMONTH($B49,0))+SUMIFS(Attendance!$AY$6:$AY$2405,Attendance!$A$6:$A$2405,">="&$B49,Attendance!$A$6:$A$2405,"<="&EOMONTH($B49,0))+SUMIFS(Attendance!$AZ$6:$AZ$2405,Attendance!$A$6:$A$2405,">="&$B49,Attendance!$A$6:$A$2405,"<="&EOMONTH($B49,0)) -> 0 | H49: =SUMIFS(Attendance!$BC$6:$BC$2405,Attendance!$A$6:$A$2405,">="&$B49,Attendance!$A$6:$A$2405,"<="&EOMONTH($B49,0)) -> 0
B50: =DATE(LvYear,2,1) -> 46054 | C50: =COUNTIFS(Attendance!$A$6:$A$2405,">="&$B50,Attendance!$A$6:$A$2405,"<="&EOMONTH($B50,0),Attendance!$B$6:$B$2405,"<>") -> 0 | D50: =SUMIFS(Attendance!$AK$6:$AK$2405,Attendance!$A$6:$A$2405,">="&$B50,Attendance!$A$6:$A$2405,"<="&EOMONTH($B50,0)) -> 0 | E50: =SUMIFS(Attendance!$AL$6:$AL$2405,Attendance!$A$6:$A$2405,">="&$B50,Attendance!$A$6:$A$2405,"<="&EOMONTH($B50,0)) -> 0 | F50: =SUMIFS(Attendance!$AN$6:$AN$2405,Attendance!$A$6:$A$2405,">="&$B50,Attendance!$A$6:$A$2405,"<="&EOMONTH($B50,0)) -> 0 | G50: =SUMIFS(Attendance!$AX$6:$AX$2405,Attendance!$A$6:$A$2405,">="&$B50,Attendance!$A$6:$A$2405,"<="&EOMONTH($B50,0))+SUMIFS(Attendance!$AY$6:$AY$2405,Attendance!$A$6:$A$2405,">="&$B50,Attendance!$A$6:$A$2405,"<="&EOMONTH($B50,0))+SUMIFS(Attendance!$AZ$6:$AZ$2405,Attendance!$A$6:$A$2405,">="&$B50,Attendance!$A$6:$A$2405,"<="&EOMONTH($B50,0)) -> 0 | H50: =SUMIFS(Attendance!$BC$6:$BC$2405,Attendance!$A$6:$A$2405,">="&$B50,Attendance!$A$6:$A$2405,"<="&EOMONTH($B50,0)) -> 0
B51: =DATE(LvYear,3,1) -> 46082 | C51: =COUNTIFS(Attendance!$A$6:$A$2405,">="&$B51,Attendance!$A$6:$A$2405,"<="&EOMONTH($B51,0),Attendance!$B$6:$B$2405,"<>") -> 0 | D51: =SUMIFS(Attendance!$AK$6:$AK$2405,Attendance!$A$6:$A$2405,">="&$B51,Attendance!$A$6:$A$2405,"<="&EOMONTH($B51,0)) -> 0 | E51: =SUMIFS(Attendance!$AL$6:$AL$2405,Attendance!$A$6:$A$2405,">="&$B51,Attendance!$A$6:$A$2405,"<="&EOMONTH($B51,0)) -> 0 | F51: =SUMIFS(Attendance!$AN$6:$AN$2405,Attendance!$A$6:$A$2405,">="&$B51,Attendance!$A$6:$A$2405,"<="&EOMONTH($B51,0)) -> 0 | G51: =SUMIFS(Attendance!$AX$6:$AX$2405,Attendance!$A$6:$A$2405,">="&$B51,Attendance!$A$6:$A$2405,"<="&EOMONTH($B51,0))+SUMIFS(Attendance!$AY$6:$AY$2405,Attendance!$A$6:$A$2405,">="&$B51,Attendance!$A$6:$A$2405,"<="&EOMONTH($B51,0))+SUMIFS(Attendance!$AZ$6:$AZ$2405,Attendance!$A$6:$A$2405,">="&$B51,Attendance!$A$6:$A$2405,"<="&EOMONTH($B51,0)) -> 0 | H51: =SUMIFS(Attendance!$BC$6:$BC$2405,Attendance!$A$6:$A$2405,">="&$B51,Attendance!$A$6:$A$2405,"<="&EOMONTH($B51,0)) -> 0
B52: =DATE(LvYear,4,1) -> 46113 | C52: =COUNTIFS(Attendance!$A$6:$A$2405,">="&$B52,Attendance!$A$6:$A$2405,"<="&EOMONTH($B52,0),Attendance!$B$6:$B$2405,"<>") -> 0 | D52: =SUMIFS(Attendance!$AK$6:$AK$2405,Attendance!$A$6:$A$2405,">="&$B52,Attendance!$A$6:$A$2405,"<="&EOMONTH($B52,0)) -> 0 | E52: =SUMIFS(Attendance!$AL$6:$AL$2405,Attendance!$A$6:$A$2405,">="&$B52,Attendance!$A$6:$A$2405,"<="&EOMONTH($B52,0)) -> 0 | F52: =SUMIFS(Attendance!$AN$6:$AN$2405,Attendance!$A$6:$A$2405,">="&$B52,Attendance!$A$6:$A$2405,"<="&EOMONTH($B52,0)) -> 0 | G52: =SUMIFS(Attendance!$AX$6:$AX$2405,Attendance!$A$6:$A$2405,">="&$B52,Attendance!$A$6:$A$2405,"<="&EOMONTH($B52,0))+SUMIFS(Attendance!$AY$6:$AY$2405,Attendance!$A$6:$A$2405,">="&$B52,Attendance!$A$6:$A$2405,"<="&EOMONTH($B52,0))+SUMIFS(Attendance!$AZ$6:$AZ$2405,Attendance!$A$6:$A$2405,">="&$B52,Attendance!$A$6:$A$2405,"<="&EOMONTH($B52,0)) -> 0 | H52: =SUMIFS(Attendance!$BC$6:$BC$2405,Attendance!$A$6:$A$2405,">="&$B52,Attendance!$A$6:$A$2405,"<="&EOMONTH($B52,0)) -> 0
B53: =DATE(LvYear,5,1) -> 46143 | C53: =COUNTIFS(Attendance!$A$6:$A$2405,">="&$B53,Attendance!$A$6:$A$2405,"<="&EOMONTH($B53,0),Attendance!$B$6:$B$2405,"<>") -> 0 | D53: =SUMIFS(Attendance!$AK$6:$AK$2405,Attendance!$A$6:$A$2405,">="&$B53,Attendance!$A$6:$A$2405,"<="&EOMONTH($B53,0)) -> 0 | E53: =SUMIFS(Attendance!$AL$6:$AL$2405,Attendance!$A$6:$A$2405,">="&$B53,Attendance!$A$6:$A$2405,"<="&EOMONTH($B53,0)) -> 0 | F53: =SUMIFS(Attendance!$AN$6:$AN$2405,Attendance!$A$6:$A$2405,">="&$B53,Attendance!$A$6:$A$2405,"<="&EOMONTH($B53,0)) -> 0 | G53: =SUMIFS(Attendance!$AX$6:$AX$2405,Attendance!$A$6:$A$2405,">="&$B53,Attendance!$A$6:$A$2405,"<="&EOMONTH($B53,0))+SUMIFS(Attendance!$AY$6:$AY$2405,Attendance!$A$6:$A$2405,">="&$B53,Attendance!$A$6:$A$2405,"<="&EOMONTH($B53,0))+SUMIFS(Attendance!$AZ$6:$AZ$2405,Attendance!$A$6:$A$2405,">="&$B53,Attendance!$A$6:$A$2405,"<="&EOMONTH($B53,0)) -> 0 | H53: =SUMIFS(Attendance!$BC$6:$BC$2405,Attendance!$A$6:$A$2405,">="&$B53,Attendance!$A$6:$A$2405,"<="&EOMONTH($B53,0)) -> 0
B54: =DATE(LvYear,6,1) -> 46174 | C54: =COUNTIFS(Attendance!$A$6:$A$2405,">="&$B54,Attendance!$A$6:$A$2405,"<="&EOMONTH($B54,0),Attendance!$B$6:$B$2405,"<>") -> 0 | D54: =SUMIFS(Attendance!$AK$6:$AK$2405,Attendance!$A$6:$A$2405,">="&$B54,Attendance!$A$6:$A$2405,"<="&EOMONTH($B54,0)) -> 0 | E54: =SUMIFS(Attendance!$AL$6:$AL$2405,Attendance!$A$6:$A$2405,">="&$B54,Attendance!$A$6:$A$2405,"<="&EOMONTH($B54,0)) -> 0 | F54: =SUMIFS(Attendance!$AN$6:$AN$2405,Attendance!$A$6:$A$2405,">="&$B54,Attendance!$A$6:$A$2405,"<="&EOMONTH($B54,0)) -> 0 | G54: =SUMIFS(Attendance!$AX$6:$AX$2405,Attendance!$A$6:$A$2405,">="&$B54,Attendance!$A$6:$A$2405,"<="&EOMONTH($B54,0))+SUMIFS(Attendance!$AY$6:$AY$2405,Attendance!$A$6:$A$2405,">="&$B54,Attendance!$A$6:$A$2405,"<="&EOMONTH($B54,0))+SUMIFS(Attendance!$AZ$6:$AZ$2405,Attendance!$A$6:$A$2405,">="&$B54,Attendance!$A$6:$A$2405,"<="&EOMONTH($B54,0)) -> 0 | H54: =SUMIFS(Attendance!$BC$6:$BC$2405,Attendance!$A$6:$A$2405,">="&$B54,Attendance!$A$6:$A$2405,"<="&EOMONTH($B54,0)) -> 0
B55: =DATE(LvYear,7,1) -> 46204 | C55: =COUNTIFS(Attendance!$A$6:$A$2405,">="&$B55,Attendance!$A$6:$A$2405,"<="&EOMONTH($B55,0),Attendance!$B$6:$B$2405,"<>") -> 0 | D55: =SUMIFS(Attendance!$AK$6:$AK$2405,Attendance!$A$6:$A$2405,">="&$B55,Attendance!$A$6:$A$2405,"<="&EOMONTH($B55,0)) -> 0 | E55: =SUMIFS(Attendance!$AL$6:$AL$2405,Attendance!$A$6:$A$2405,">="&$B55,Attendance!$A$6:$A$2405,"<="&EOMONTH($B55,0)) -> 0 | F55: =SUMIFS(Attendance!$AN$6:$AN$2405,Attendance!$A$6:$A$2405,">="&$B55,Attendance!$A$6:$A$2405,"<="&EOMONTH($B55,0)) -> 0 | G55: =SUMIFS(Attendance!$AX$6:$AX$2405,Attendance!$A$6:$A$2405,">="&$B55,Attendance!$A$6:$A$2405,"<="&EOMONTH($B55,0))+SUMIFS(Attendance!$AY$6:$AY$2405,Attendance!$A$6:$A$2405,">="&$B55,Attendance!$A$6:$A$2405,"<="&EOMONTH($B55,0))+SUMIFS(Attendance!$AZ$6:$AZ$2405,Attendance!$A$6:$A$2405,">="&$B55,Attendance!$A$6:$A$2405,"<="&EOMONTH($B55,0)) -> 0 | H55: =SUMIFS(Attendance!$BC$6:$BC$2405,Attendance!$A$6:$A$2405,">="&$B55,Attendance!$A$6:$A$2405,"<="&EOMONTH($B55,0)) -> 0
B56: =DATE(LvYear,8,1) -> 46235 | C56: =COUNTIFS(Attendance!$A$6:$A$2405,">="&$B56,Attendance!$A$6:$A$2405,"<="&EOMONTH($B56,0),Attendance!$B$6:$B$2405,"<>") -> 0 | D56: =SUMIFS(Attendance!$AK$6:$AK$2405,Attendance!$A$6:$A$2405,">="&$B56,Attendance!$A$6:$A$2405,"<="&EOMONTH($B56,0)) -> 0 | E56: =SUMIFS(Attendance!$AL$6:$AL$2405,Attendance!$A$6:$A$2405,">="&$B56,Attendance!$A$6:$A$2405,"<="&EOMONTH($B56,0)) -> 0 | F56: =SUMIFS(Attendance!$AN$6:$AN$2405,Attendance!$A$6:$A$2405,">="&$B56,Attendance!$A$6:$A$2405,"<="&EOMONTH($B56,0)) -> 0 | G56: =SUMIFS(Attendance!$AX$6:$AX$2405,Attendance!$A$6:$A$2405,">="&$B56,Attendance!$A$6:$A$2405,"<="&EOMONTH($B56,0))+SUMIFS(Attendance!$AY$6:$AY$2405,Attendance!$A$6:$A$2405,">="&$B56,Attendance!$A$6:$A$2405,"<="&EOMONTH($B56,0))+SUMIFS(Attendance!$AZ$6:$AZ$2405,Attendance!$A$6:$A$2405,">="&$B56,Attendance!$A$6:$A$2405,"<="&EOMONTH($B56,0)) -> 0 | H56: =SUMIFS(Attendance!$BC$6:$BC$2405,Attendance!$A$6:$A$2405,">="&$B56,Attendance!$A$6:$A$2405,"<="&EOMONTH($B56,0)) -> 0
B57: =DATE(LvYear,9,1) -> 46266 | C57: =COUNTIFS(Attendance!$A$6:$A$2405,">="&$B57,Attendance!$A$6:$A$2405,"<="&EOMONTH($B57,0),Attendance!$B$6:$B$2405,"<>") -> 0 | D57: =SUMIFS(Attendance!$AK$6:$AK$2405,Attendance!$A$6:$A$2405,">="&$B57,Attendance!$A$6:$A$2405,"<="&EOMONTH($B57,0)) -> 0 | E57: =SUMIFS(Attendance!$AL$6:$AL$2405,Attendance!$A$6:$A$2405,">="&$B57,Attendance!$A$6:$A$2405,"<="&EOMONTH($B57,0)) -> 0 | F57: =SUMIFS(Attendance!$AN$6:$AN$2405,Attendance!$A$6:$A$2405,">="&$B57,Attendance!$A$6:$A$2405,"<="&EOMONTH($B57,0)) -> 0 | G57: =SUMIFS(Attendance!$AX$6:$AX$2405,Attendance!$A$6:$A$2405,">="&$B57,Attendance!$A$6:$A$2405,"<="&EOMONTH($B57,0))+SUMIFS(Attendance!$AY$6:$AY$2405,Attendance!$A$6:$A$2405,">="&$B57,Attendance!$A$6:$A$2405,"<="&EOMONTH($B57,0))+SUMIFS(Attendance!$AZ$6:$AZ$2405,Attendance!$A$6:$A$2405,">="&$B57,Attendance!$A$6:$A$2405,"<="&EOMONTH($B57,0)) -> 0 | H57: =SUMIFS(Attendance!$BC$6:$BC$2405,Attendance!$A$6:$A$2405,">="&$B57,Attendance!$A$6:$A$2405,"<="&EOMONTH($B57,0)) -> 0
B58: =DATE(LvYear,10,1) -> 46296 | C58: =COUNTIFS(Attendance!$A$6:$A$2405,">="&$B58,Attendance!$A$6:$A$2405,"<="&EOMONTH($B58,0),Attendance!$B$6:$B$2405,"<>") -> 0 | D58: =SUMIFS(Attendance!$AK$6:$AK$2405,Attendance!$A$6:$A$2405,">="&$B58,Attendance!$A$6:$A$2405,"<="&EOMONTH($B58,0)) -> 0 | E58: =SUMIFS(Attendance!$AL$6:$AL$2405,Attendance!$A$6:$A$2405,">="&$B58,Attendance!$A$6:$A$2405,"<="&EOMONTH($B58,0)) -> 0 | F58: =SUMIFS(Attendance!$AN$6:$AN$2405,Attendance!$A$6:$A$2405,">="&$B58,Attendance!$A$6:$A$2405,"<="&EOMONTH($B58,0)) -> 0 | G58: =SUMIFS(Attendance!$AX$6:$AX$2405,Attendance!$A$6:$A$2405,">="&$B58,Attendance!$A$6:$A$2405,"<="&EOMONTH($B58,0))+SUMIFS(Attendance!$AY$6:$AY$2405,Attendance!$A$6:$A$2405,">="&$B58,Attendance!$A$6:$A$2405,"<="&EOMONTH($B58,0))+SUMIFS(Attendance!$AZ$6:$AZ$2405,Attendance!$A$6:$A$2405,">="&$B58,Attendance!$A$6:$A$2405,"<="&EOMONTH($B58,0)) -> 0 | H58: =SUMIFS(Attendance!$BC$6:$BC$2405,Attendance!$A$6:$A$2405,">="&$B58,Attendance!$A$6:$A$2405,"<="&EOMONTH($B58,0)) -> 0
B59: =DATE(LvYear,11,1) -> 46327 | C59: =COUNTIFS(Attendance!$A$6:$A$2405,">="&$B59,Attendance!$A$6:$A$2405,"<="&EOMONTH($B59,0),Attendance!$B$6:$B$2405,"<>") -> 0 | D59: =SUMIFS(Attendance!$AK$6:$AK$2405,Attendance!$A$6:$A$2405,">="&$B59,Attendance!$A$6:$A$2405,"<="&EOMONTH($B59,0)) -> 0 | E59: =SUMIFS(Attendance!$AL$6:$AL$2405,Attendance!$A$6:$A$2405,">="&$B59,Attendance!$A$6:$A$2405,"<="&EOMONTH($B59,0)) -> 0 | F59: =SUMIFS(Attendance!$AN$6:$AN$2405,Attendance!$A$6:$A$2405,">="&$B59,Attendance!$A$6:$A$2405,"<="&EOMONTH($B59,0)) -> 0 | G59: =SUMIFS(Attendance!$AX$6:$AX$2405,Attendance!$A$6:$A$2405,">="&$B59,Attendance!$A$6:$A$2405,"<="&EOMONTH($B59,0))+SUMIFS(Attendance!$AY$6:$AY$2405,Attendance!$A$6:$A$2405,">="&$B59,Attendance!$A$6:$A$2405,"<="&EOMONTH($B59,0))+SUMIFS(Attendance!$AZ$6:$AZ$2405,Attendance!$A$6:$A$2405,">="&$B59,Attendance!$A$6:$A$2405,"<="&EOMONTH($B59,0)) -> 0 | H59: =SUMIFS(Attendance!$BC$6:$BC$2405,Attendance!$A$6:$A$2405,">="&$B59,Attendance!$A$6:$A$2405,"<="&EOMONTH($B59,0)) -> 0
B60: =DATE(LvYear,12,1) -> 46357 | C60: =COUNTIFS(Attendance!$A$6:$A$2405,">="&$B60,Attendance!$A$6:$A$2405,"<="&EOMONTH($B60,0),Attendance!$B$6:$B$2405,"<>") -> 0 | D60: =SUMIFS(Attendance!$AK$6:$AK$2405,Attendance!$A$6:$A$2405,">="&$B60,Attendance!$A$6:$A$2405,"<="&EOMONTH($B60,0)) -> 0 | E60: =SUMIFS(Attendance!$AL$6:$AL$2405,Attendance!$A$6:$A$2405,">="&$B60,Attendance!$A$6:$A$2405,"<="&EOMONTH($B60,0)) -> 0 | F60: =SUMIFS(Attendance!$AN$6:$AN$2405,Attendance!$A$6:$A$2405,">="&$B60,Attendance!$A$6:$A$2405,"<="&EOMONTH($B60,0)) -> 0 | G60: =SUMIFS(Attendance!$AX$6:$AX$2405,Attendance!$A$6:$A$2405,">="&$B60,Attendance!$A$6:$A$2405,"<="&EOMONTH($B60,0))+SUMIFS(Attendance!$AY$6:$AY$2405,Attendance!$A$6:$A$2405,">="&$B60,Attendance!$A$6:$A$2405,"<="&EOMONTH($B60,0))+SUMIFS(Attendance!$AZ$6:$AZ$2405,Attendance!$A$6:$A$2405,">="&$B60,Attendance!$A$6:$A$2405,"<="&EOMONTH($B60,0)) -> 0 | H60: =SUMIFS(Attendance!$BC$6:$BC$2405,Attendance!$A$6:$A$2405,">="&$B60,Attendance!$A$6:$A$2405,"<="&EOMONTH($B60,0)) -> 0
B61: TOTAL | C61: =SUM(C49:C60) -> 0 | D61: =SUM(D49:D60) -> 0 | E61: =SUM(E49:E60) -> 0 | F61: =SUM(F49:F60) -> 0 | G61: =SUM(G49:G60) -> 0 | H61: =SUM(H49:H60) -> 0

Sheet Employee List
A1: ="EMPLOYEE LIST - "&Settings!$C$5 -> EMPLOYEE LIST - Your Company Name
A2: How to use: list each employee once (first blank row). Leave Record and Attendance read names from here. Type the Exit Date when someone leaves - Status turns to Exited. Employment Type is automatic (Permanent after the confirmation days in Settings, else Probation).
B3: Active | C3: =COUNTIF(M_status,"Active") -> 0 | D3: Exited | E3: =COUNTIF(M_status,"Exited") -> 0 | F3: Total records | G3: =COUNTA(M_emp) -> 0
A4: EMPLOYEE DETAILS
A5: Sr No | B5: Emp Code | C5: Employee Name | D5: Status | E5: Designation | F5: Department | G5: Location | H5: Employment Type (auto) | I5: DOJ | J5: Exit Date
A6: =IF(B6="","",ROW()-5) | D6: =IF(B6="","",IF(J6="","Active","Exited")) | H6: =IF(OR(B6="",I6=""),"",IF(IF(J6="",AsOf,J6)-I6>=Settings!$C$13,"Permanent","Probation"))
A7: =IF(B7="","",ROW()-5) | D7: =IF(B7="","",IF(J7="","Active","Exited")) | H7: =IF(OR(B7="",I7=""),"",IF(IF(J7="",AsOf,J7)-I7>=Settings!$C$13,"Permanent","Probation"))
A8: =IF(B8="","",ROW()-5) | D8: =IF(B8="","",IF(J8="","Active","Exited")) | H8: =IF(OR(B8="",I8=""),"",IF(IF(J8="",AsOf,J8)-I8>=Settings!$C$13,"Permanent","Probation"))
A9: =IF(B9="","",ROW()-5) | D9: =IF(B9="","",IF(J9="","Active","Exited")) | H9: =IF(OR(B9="",I9=""),"",IF(IF(J9="",AsOf,J9)-I9>=Settings!$C$13,"Permanent","Probation"))
A10: =IF(B10="","",ROW()-5) | D10: =IF(B10="","",IF(J10="","Active","Exited")) | H10: =IF(OR(B10="",I10=""),"",IF(IF(J10="",AsOf,J10)-I10>=Settings!$C$13,"Permanent","Probation"))
A11: =IF(B11="","",ROW()-5) | D11: =IF(B11="","",IF(J11="","Active","Exited")) | H11: =IF(OR(B11="",I11=""),"",IF(IF(J11="",AsOf,J11)-I11>=Settings!$C$13,"Permanent","Probation"))
A12: =IF(B12="","",ROW()-5) | D12: =IF(B12="","",IF(J12="","Active","Exited")) | H12: =IF(OR(B12="",I12=""),"",IF(IF(J12="",AsOf,J12)-I12>=Settings!$C$13,"Permanent","Probation"))
A13: =IF(B13="","",ROW()-5) | D13: =IF(B13="","",IF(J13="","Active","Exited")) | H13: =IF(OR(B13="",I13=""),"",IF(IF(J13="",AsOf,J13)-I13>=Settings!$C$13,"Permanent","Probation"))
A14: =IF(B14="","",ROW()-5) | D14: =IF(B14="","",IF(J14="","Active","Exited")) | H14: =IF(OR(B14="",I14=""),"",IF(IF(J14="",AsOf,J14)-I14>=Settings!$C$13,"Permanent","Probation"))
A15: =IF(B15="","",ROW()-5) | D15: =IF(B15="","",IF(J15="","Active","Exited")) | H15: =IF(OR(B15="",I15=""),"",IF(IF(J15="",AsOf,J15)-I15>=Settings!$C$13,"Permanent","Probation"))
A16: =IF(B16="","",ROW()-5) | D16: =IF(B16="","",IF(J16="","Active","Exited")) | H16: =IF(OR(B16="",I16=""),"",IF(IF(J16="",AsOf,J16)-I16>=Settings!$C$13,"Permanent","Probation"))
A17: =IF(B17="","",ROW()-5) | D17: =IF(B17="","",IF(J17="","Active","Exited")) | H17: =IF(OR(B17="",I17=""),"",IF(IF(J17="",AsOf,J17)-I17>=Settings!$C$13,"Permanent","Probation"))
... A505: =IF(B505="","",ROW()-5) | D505: =IF(B505="","",IF(J505="","Active","Exited")) | H505: =IF(OR(B505="",I505=""),"",IF(IF(J505="",AsOf,J505)-I505>=Settings!$C$13,"Permanent","Probation"))

Sheet Attendance
A1: ="MONTHLY ATTENDANCE - "&Settings!$C$5 -> MONTHLY ATTENDANCE - Your Company Name
A2: How to use: one row per employee per month. Type the 1st of the month in Month (e.g. 01-Oct-2026) and the Emp Code - name, department and location fill themselves. Then pick a code in each day cell (see Settings for codes). Grey cells = Sundays / days not in the month.
A3: Tip: filter Month to work on one month at a time.
A5: Month | B5: Emp Code | C5: Employee Name | D5: Department | E5: Location | F5: 1 | G5: 2 | H5: 3 | I5: 4 | J5: 5 | K5: 6 | L5: 7 | M5: 8 | N5: 9 | O5: 10 | P5: 11 | Q5: 12 | R5: 13 | S5: 14 | T5: 15 | U5: 16 | V5: 17 | W5: 18 | X5: 19 | Y5: 20 | Z5: 21 | AA5: 22 | AB5: 23 | AC5: 24 | AD5: 25 | AE5: 26 | AF5: 27 | AG5: 28 | AH5: 29 | AI5: 30 | AJ5: 31 | AK5: PRESENT | AL5: ABSENT | AM5: HALF ABSENT | AN5: LATE | AO5: PAID LEAVE | AP5: CASUAL LEAVE | AQ5: SICK LEAVE | AR5: COMP OFF | AS5: HALF P/L | AT5: HALF C/L | AU5: WEEKLY OFF | AV5: PUBLIC HOLIDAY | AW5: TRAINING DAYS | AX5: TOTAL P/L | AY5: TOTAL S/L | AZ5: TOTAL C/L | BA5: GROSS PAYABLE DAYS | BB5: LATE DEDUCTION (days) | BC5: NET PAYABLE DAYS | BD5: UNMARKED DAYS
C6: =IF($B6="","",IFERROR(INDEX(M_name,MATCH($B6,M_emp,0)),"Code not found")) | D6: =IF($B6="","",IFERROR(INDEX(M_dept,MATCH($B6,M_emp,0)),"")) | E6: =IF($B6="","",IFERROR(INDEX(M_loc,MATCH($B6,M_emp,0)),"")) | AK6: =IF($B6="","",COUNTIF($F6:$AJ6,"P")) | AL6: =IF($B6="","",COUNTIF($F6:$AJ6,"A")) | AM6: =IF($B6="","",COUNTIF($F6:$AJ6,"HA")) | AN6: =IF($B6="","",COUNTIF($F6:$AJ6,"L")) | AO6: =IF($B6="","",COUNTIF($F6:$AJ6,"PL")) | AP6: =IF($B6="","",COUNTIF($F6:$AJ6,"CL")) | AQ6: =IF($B6="","",COUNTIF($F6:$AJ6,"SL")) | AR6: =IF($B6="","",COUNTIF($F6:$AJ6,"CO")) | AS6: =IF($B6="","",COUNTIF($F6:$AJ6,"HPL")) | AT6: =IF($B6="","",COUNTIF($F6:$AJ6,"HCL")) | AU6: =IF($B6="","",COUNTIF($F6:$AJ6,"WO")) | AV6: =IF($B6="","",COUNTIF($F6:$AJ6,"PH")) | AW6: =IF($B6="","",COUNTIF($F6:$AJ6,"TR")) | AX6: =IF($B6="","",AO6+AS6/2) | AY6: =IF($B6="","",AQ6) | AZ6: =IF($B6="","",AP6+AT6/2) | BA6: =IF($B6="","",AK6+AN6+AM6/2+AO6+AP6+AQ6+AR6+AS6+AT6+AU6+AV6+AW6) | BB6: =IF($B6="","",MAX(0,AN6-Settings!$C$16)*Settings!$C$17) | BC6: =IF($B6="","",BA6-BB6) | BD6: =IF(OR($B6="",$A6=""),"",DAY(EOMONTH($A6,0))-COUNTA($F6:$AJ6))
C7: =IF($B7="","",IFERROR(INDEX(M_name,MATCH($B7,M_emp,0)),"Code not found")) | D7: =IF($B7="","",IFERROR(INDEX(M_dept,MATCH($B7,M_emp,0)),"")) | E7: =IF($B7="","",IFERROR(INDEX(M_loc,MATCH($B7,M_emp,0)),"")) | AK7: =IF($B7="","",COUNTIF($F7:$AJ7,"P")) | AL7: =IF($B7="","",COUNTIF($F7:$AJ7,"A")) | AM7: =IF($B7="","",COUNTIF($F7:$AJ7,"HA")) | AN7: =IF($B7="","",COUNTIF($F7:$AJ7,"L")) | AO7: =IF($B7="","",COUNTIF($F7:$AJ7,"PL")) | AP7: =IF($B7="","",COUNTIF($F7:$AJ7,"CL")) | AQ7: =IF($B7="","",COUNTIF($F7:$AJ7,"SL")) | AR7: =IF($B7="","",COUNTIF($F7:$AJ7,"CO")) | AS7: =IF($B7="","",COUNTIF($F7:$AJ7,"HPL")) | AT7: =IF($B7="","",COUNTIF($F7:$AJ7,"HCL")) | AU7: =IF($B7="","",COUNTIF($F7:$AJ7,"WO")) | AV7: =IF($B7="","",COUNTIF($F7:$AJ7,"PH")) | AW7: =IF($B7="","",COUNTIF($F7:$AJ7,"TR")) | AX7: =IF($B7="","",AO7+AS7/2) | AY7: =IF($B7="","",AQ7) | AZ7: =IF($B7="","",AP7+AT7/2) | BA7: =IF($B7="","",AK7+AN7+AM7/2+AO7+AP7+AQ7+AR7+AS7+AT7+AU7+AV7+AW7) | BB7: =IF($B7="","",MAX(0,AN7-Settings!$C$16)*Settings!$C$17) | BC7: =IF($B7="","",BA7-BB7) | BD7: =IF(OR($B7="",$A7=""),"",DAY(EOMONTH($A7,0))-COUNTA($F7:$AJ7))
C8: =IF($B8="","",IFERROR(INDEX(M_name,MATCH($B8,M_emp,0)),"Code not found")) | D8: =IF($B8="","",IFERROR(INDEX(M_dept,MATCH($B8,M_emp,0)),"")) | E8: =IF($B8="","",IFERROR(INDEX(M_loc,MATCH($B8,M_emp,0)),"")) | AK8: =IF($B8="","",COUNTIF($F8:$AJ8,"P")) | AL8: =IF($B8="","",COUNTIF($F8:$AJ8,"A")) | AM8: =IF($B8="","",COUNTIF($F8:$AJ8,"HA")) | AN8: =IF($B8="","",COUNTIF($F8:$AJ8,"L")) | AO8: =IF($B8="","",COUNTIF($F8:$AJ8,"PL")) | AP8: =IF($B8="","",COUNTIF($F8:$AJ8,"CL")) | AQ8: =IF($B8="","",COUNTIF($F8:$AJ8,"SL")) | AR8: =IF($B8="","",COUNTIF($F8:$AJ8,"CO")) | AS8: =IF($B8="","",COUNTIF($F8:$AJ8,"HPL")) | AT8: =IF($B8="","",COUNTIF($F8:$AJ8,"HCL")) | AU8: =IF($B8="","",COUNTIF($F8:$AJ8,"WO")) | AV8: =IF($B8="","",COUNTIF($F8:$AJ8,"PH")) | AW8: =IF($B8="","",COUNTIF($F8:$AJ8,"TR")) | AX8: =IF($B8="","",AO8+AS8/2) | AY8: =IF($B8="","",AQ8) | AZ8: =IF($B8="","",AP8+AT8/2) | BA8: =IF($B8="","",AK8+AN8+AM8/2+AO8+AP8+AQ8+AR8+AS8+AT8+AU8+AV8+AW8) | BB8: =IF($B8="","",MAX(0,AN8-Settings!$C$16)*Settings!$C$17) | BC8: =IF($B8="","",BA8-BB8) | BD8: =IF(OR($B8="",$A8=""),"",DAY(EOMONTH($A8,0))-COUNTA($F8:$AJ8))
C9: =IF($B9="","",IFERROR(INDEX(M_name,MATCH($B9,M_emp,0)),"Code not found")) | D9: =IF($B9="","",IFERROR(INDEX(M_dept,MATCH($B9,M_emp,0)),"")) | E9: =IF($B9="","",IFERROR(INDEX(M_loc,MATCH($B9,M_emp,0)),"")) | AK9: =IF($B9="","",COUNTIF($F9:$AJ9,"P")) | AL9: =IF($B9="","",COUNTIF($F9:$AJ9,"A")) | AM9: =IF($B9="","",COUNTIF($F9:$AJ9,"HA")) | AN9: =IF($B9="","",COUNTIF($F9:$AJ9,"L")) | AO9: =IF($B9="","",COUNTIF($F9:$AJ9,"PL")) | AP9: =IF($B9="","",COUNTIF($F9:$AJ9,"CL")) | AQ9: =IF($B9="","",COUNTIF($F9:$AJ9,"SL")) | AR9: =IF($B9="","",COUNTIF($F9:$AJ9,"CO")) | AS9: =IF($B9="","",COUNTIF($F9:$AJ9,"HPL")) | AT9: =IF($B9="","",COUNTIF($F9:$AJ9,"HCL")) | AU9: =IF($B9="","",COUNTIF($F9:$AJ9,"WO")) | AV9: =IF($B9="","",COUNTIF($F9:$AJ9,"PH")) | AW9: =IF($B9="","",COUNTIF($F9:$AJ9,"TR")) | AX9: =IF($B9="","",AO9+AS9/2) | AY9: =IF($B9="","",AQ9) | AZ9: =IF($B9="","",AP9+AT9/2) | BA9: =IF($B9="","",AK9+AN9+AM9/2+AO9+AP9+AQ9+AR9+AS9+AT9+AU9+AV9+AW9) | BB9: =IF($B9="","",MAX(0,AN9-Settings!$C$16)*Settings!$C$17) | BC9: =IF($B9="","",BA9-BB9) | BD9: =IF(OR($B9="",$A9=""),"",DAY(EOMONTH($A9,0))-COUNTA($F9:$AJ9))
C10: =IF($B10="","",IFERROR(INDEX(M_name,MATCH($B10,M_emp,0)),"Code not found")) | D10: =IF($B10="","",IFERROR(INDEX(M_dept,MATCH($B10,M_emp,0)),"")) | E10: =IF($B10="","",IFERROR(INDEX(M_loc,MATCH($B10,M_emp,0)),"")) | AK10: =IF($B10="","",COUNTIF($F10:$AJ10,"P")) | AL10: =IF($B10="","",COUNTIF($F10:$AJ10,"A")) | AM10: =IF($B10="","",COUNTIF($F10:$AJ10,"HA")) | AN10: =IF($B10="","",COUNTIF($F10:$AJ10,"L")) | AO10: =IF($B10="","",COUNTIF($F10:$AJ10,"PL")) | AP10: =IF($B10="","",COUNTIF($F10:$AJ10,"CL")) | AQ10: =IF($B10="","",COUNTIF($F10:$AJ10,"SL")) | AR10: =IF($B10="","",COUNTIF($F10:$AJ10,"CO")) | AS10: =IF($B10="","",COUNTIF($F10:$AJ10,"HPL")) | AT10: =IF($B10="","",COUNTIF($F10:$AJ10,"HCL")) | AU10: =IF($B10="","",COUNTIF($F10:$AJ10,"WO")) | AV10: =IF($B10="","",COUNTIF($F10:$AJ10,"PH")) | AW10: =IF($B10="","",COUNTIF($F10:$AJ10,"TR")) | AX10: =IF($B10="","",AO10+AS10/2) | AY10: =IF($B10="","",AQ10) | AZ10: =IF($B10="","",AP10+AT10/2) | BA10: =IF($B10="","",AK10+AN10+AM10/2+AO10+AP10+AQ10+AR10+AS10+AT10+AU10+AV10+AW10) | BB10: =IF($B10="","",MAX(0,AN10-Settings!$C$16)*Settings!$C$17) | BC10: =IF($B10="","",BA10-BB10) | BD10: =IF(OR($B10="",$A10=""),"",DAY(EOMONTH($A10,0))-COUNTA($F10:$AJ10))
C11: =IF($B11="","",IFERROR(INDEX(M_name,MATCH($B11,M_emp,0)),"Code not found")) | D11: =IF($B11="","",IFERROR(INDEX(M_dept,MATCH($B11,M_emp,0)),"")) | E11: =IF($B11="","",IFERROR(INDEX(M_loc,MATCH($B11,M_emp,0)),"")) | AK11: =IF($B11="","",COUNTIF($F11:$AJ11,"P")) | AL11: =IF($B11="","",COUNTIF($F11:$AJ11,"A")) | AM11: =IF($B11="","",COUNTIF($F11:$AJ11,"HA")) | AN11: =IF($B11="","",COUNTIF($F11:$AJ11,"L")) | AO11: =IF($B11="","",COUNTIF($F11:$AJ11,"PL")) | AP11: =IF($B11="","",COUNTIF($F11:$AJ11,"CL")) | AQ11: =IF($B11="","",COUNTIF($F11:$AJ11,"SL")) | AR11: =IF($B11="","",COUNTIF($F11:$AJ11,"CO")) | AS11: =IF($B11="","",COUNTIF($F11:$AJ11,"HPL")) | AT11: =IF($B11="","",COUNTIF($F11:$AJ11,"HCL")) | AU11: =IF($B11="","",COUNTIF($F11:$AJ11,"WO")) | AV11: =IF($B11="","",COUNTIF($F11:$AJ11,"PH")) | AW11: =IF($B11="","",COUNTIF($F11:$AJ11,"TR")) | AX11: =IF($B11="","",AO11+AS11/2) | AY11: =IF($B11="","",AQ11) | AZ11: =IF($B11="","",AP11+AT11/2) | BA11: =IF($B11="","",AK11+AN11+AM11/2+AO11+AP11+AQ11+AR11+AS11+AT11+AU11+AV11+AW11) | BB11: =IF($B11="","",MAX(0,AN11-Settings!$C$16)*Settings!$C$17) | BC11: =IF($B11="","",BA11-BB11) | BD11: =IF(OR($B11="",$A11=""),"",DAY(EOMONTH($A11,0))-COUNTA($F11:$AJ11))
C12: =IF($B12="","",IFERROR(INDEX(M_name,MATCH($B12,M_emp,0)),"Code not found")) | D12: =IF($B12="","",IFERROR(INDEX(M_dept,MATCH($B12,M_emp,0)),"")) | E12: =IF($B12="","",IFERROR(INDEX(M_loc,MATCH($B12,M_emp,0)),"")) | AK12: =IF($B12="","",COUNTIF($F12:$AJ12,"P")) | AL12: =IF($B12="","",COUNTIF($F12:$AJ12,"A")) | AM12: =IF($B12="","",COUNTIF($F12:$AJ12,"HA")) | AN12: =IF($B12="","",COUNTIF($F12:$AJ12,"L")) | AO12: =IF($B12="","",COUNTIF($F12:$AJ12,"PL")) | AP12: =IF($B12="","",COUNTIF($F12:$AJ12,"CL")) | AQ12: =IF($B12="","",COUNTIF($F12:$AJ12,"SL")) | AR12: =IF($B12="","",COUNTIF($F12:$AJ12,"CO")) | AS12: =IF($B12="","",COUNTIF($F12:$AJ12,"HPL")) | AT12: =IF($B12="","",COUNTIF($F12:$AJ12,"HCL")) | AU12: =IF($B12="","",COUNTIF($F12:$AJ12,"WO")) | AV12: =IF($B12="","",COUNTIF($F12:$AJ12,"PH")) | AW12: =IF($B12="","",COUNTIF($F12:$AJ12,"TR")) | AX12: =IF($B12="","",AO12+AS12/2) | AY12: =IF($B12="","",AQ12) | AZ12: =IF($B12="","",AP12+AT12/2) | BA12: =IF($B12="","",AK12+AN12+AM12/2+AO12+AP12+AQ12+AR12+AS12+AT12+AU12+AV12+AW12) | BB12: =IF($B12="","",MAX(0,AN12-Settings!$C$16)*Settings!$C$17) | BC12: =IF($B12="","",BA12-BB12) | BD12: =IF(OR($B12="",$A12=""),"",DAY(EOMONTH($A12,0))-COUNTA($F12:$AJ12))
C13: =IF($B13="","",IFERROR(INDEX(M_name,MATCH($B13,M_emp,0)),"Code not found")) | D13: =IF($B13="","",IFERROR(INDEX(M_dept,MATCH($B13,M_emp,0)),"")) | E13: =IF($B13="","",IFERROR(INDEX(M_loc,MATCH($B13,M_emp,0)),"")) | AK13: =IF($B13="","",COUNTIF($F13:$AJ13,"P")) | AL13: =IF($B13="","",COUNTIF($F13:$AJ13,"A")) | AM13: =IF($B13="","",COUNTIF($F13:$AJ13,"HA")) | AN13: =IF($B13="","",COUNTIF($F13:$AJ13,"L")) | AO13: =IF($B13="","",COUNTIF($F13:$AJ13,"PL")) | AP13: =IF($B13="","",COUNTIF($F13:$AJ13,"CL")) | AQ13: =IF($B13="","",COUNTIF($F13:$AJ13,"SL")) | AR13: =IF($B13="","",COUNTIF($F13:$AJ13,"CO")) | AS13: =IF($B13="","",COUNTIF($F13:$AJ13,"HPL")) | AT13: =IF($B13="","",COUNTIF($F13:$AJ13,"HCL")) | AU13: =IF($B13="","",COUNTIF($F13:$AJ13,"WO")) | AV13: =IF($B13="","",COUNTIF($F13:$AJ13,"PH")) | AW13: =IF($B13="","",COUNTIF($F13:$AJ13,"TR")) | AX13: =IF($B13="","",AO13+AS13/2) | AY13: =IF($B13="","",AQ13) | AZ13: =IF($B13="","",AP13+AT13/2) | BA13: =IF($B13="","",AK13+AN13+AM13/2+AO13+AP13+AQ13+AR13+AS13+AT13+AU13+AV13+AW13) | BB13: =IF($B13="","",MAX(0,AN13-Settings!$C$16)*Settings!$C$17) | BC13: =IF($B13="","",BA13-BB13) | BD13: =IF(OR($B13="",$A13=""),"",DAY(EOMONTH($A13,0))-COUNTA($F13:$AJ13))
C14: =IF($B14="","",IFERROR(INDEX(M_name,MATCH($B14,M_emp,0)),"Code not found")) | D14: =IF($B14="","",IFERROR(INDEX(M_dept,MATCH($B14,M_emp,0)),"")) | E14: =IF($B14="","",IFERROR(INDEX(M_loc,MATCH($B14,M_emp,0)),"")) | AK14: =IF($B14="","",COUNTIF($F14:$AJ14,"P")) | AL14: =IF($B14="","",COUNTIF($F14:$AJ14,"A")) | AM14: =IF($B14="","",COUNTIF($F14:$AJ14,"HA")) | AN14: =IF($B14="","",COUNTIF($F14:$AJ14,"L")) | AO14: =IF($B14="","",COUNTIF($F14:$AJ14,"PL")) | AP14: =IF($B14="","",COUNTIF($F14:$AJ14,"CL")) | AQ14: =IF($B14="","",COUNTIF($F14:$AJ14,"SL")) | AR14: =IF($B14="","",COUNTIF($F14:$AJ14,"CO")) | AS14: =IF($B14="","",COUNTIF($F14:$AJ14,"HPL")) | AT14: =IF($B14="","",COUNTIF($F14:$AJ14,"HCL")) | AU14: =IF($B14="","",COUNTIF($F14:$AJ14,"WO")) | AV14: =IF($B14="","",COUNTIF($F14:$AJ14,"PH")) | AW14: =IF($B14="","",COUNTIF($F14:$AJ14,"TR")) | AX14: =IF($B14="","",AO14+AS14/2) | AY14: =IF($B14="","",AQ14) | AZ14: =IF($B14="","",AP14+AT14/2) | BA14: =IF($B14="","",AK14+AN14+AM14/2+AO14+AP14+AQ14+AR14+AS14+AT14+AU14+AV14+AW14) | BB14: =IF($B14="","",MAX(0,AN14-Settings!$C$16)*Settings!$C$17) | BC14: =IF($B14="","",BA14-BB14) | BD14: =IF(OR($B14="",$A14=""),"",DAY(EOMONTH($A14,0))-COUNTA($F14:$AJ14))
C15: =IF($B15="","",IFERROR(INDEX(M_name,MATCH($B15,M_emp,0)),"Code not found")) | D15: =IF($B15="","",IFERROR(INDEX(M_dept,MATCH($B15,M_emp,0)),"")) | E15: =IF($B15="","",IFERROR(INDEX(M_loc,MATCH($B15,M_emp,0)),"")) | AK15: =IF($B15="","",COUNTIF($F15:$AJ15,"P")) | AL15: =IF($B15="","",COUNTIF($F15:$AJ15,"A")) | AM15: =IF($B15="","",COUNTIF($F15:$AJ15,"HA")) | AN15: =IF($B15="","",COUNTIF($F15:$AJ15,"L")) | AO15: =IF($B15="","",COUNTIF($F15:$AJ15,"PL")) | AP15: =IF($B15="","",COUNTIF($F15:$AJ15,"CL")) | AQ15: =IF($B15="","",COUNTIF($F15:$AJ15,"SL")) | AR15: =IF($B15="","",COUNTIF($F15:$AJ15,"CO")) | AS15: =IF($B15="","",COUNTIF($F15:$AJ15,"HPL")) | AT15: =IF($B15="","",COUNTIF($F15:$AJ15,"HCL")) | AU15: =IF($B15="","",COUNTIF($F15:$AJ15,"WO")) | AV15: =IF($B15="","",COUNTIF($F15:$AJ15,"PH")) | AW15: =IF($B15="","",COUNTIF($F15:$AJ15,"TR")) | AX15: =IF($B15="","",AO15+AS15/2) | AY15: =IF($B15="","",AQ15) | AZ15: =IF($B15="","",AP15+AT15/2) | BA15: =IF($B15="","",AK15+AN15+AM15/2+AO15+AP15+AQ15+AR15+AS15+AT15+AU15+AV15+AW15) | BB15: =IF($B15="","",MAX(0,AN15-Settings!$C$16)*Settings!$C$17) | BC15: =IF($B15="","",BA15-BB15) | BD15: =IF(OR($B15="",$A15=""),"",DAY(EOMONTH($A15,0))-COUNTA($F15:$AJ15))
C16: =IF($B16="","",IFERROR(INDEX(M_name,MATCH($B16,M_emp,0)),"Code not found")) | D16: =IF($B16="","",IFERROR(INDEX(M_dept,MATCH($B16,M_emp,0)),"")) | E16: =IF($B16="","",IFERROR(INDEX(M_loc,MATCH($B16,M_emp,0)),"")) | AK16: =IF($B16="","",COUNTIF($F16:$AJ16,"P")) | AL16: =IF($B16="","",COUNTIF($F16:$AJ16,"A")) | AM16: =IF($B16="","",COUNTIF($F16:$AJ16,"HA")) | AN16: =IF($B16="","",COUNTIF($F16:$AJ16,"L")) | AO16: =IF($B16="","",COUNTIF($F16:$AJ16,"PL")) | AP16: =IF($B16="","",COUNTIF($F16:$AJ16,"CL")) | AQ16: =IF($B16="","",COUNTIF($F16:$AJ16,"SL")) | AR16: =IF($B16="","",COUNTIF($F16:$AJ16,"CO")) | AS16: =IF($B16="","",COUNTIF($F16:$AJ16,"HPL")) | AT16: =IF($B16="","",COUNTIF($F16:$AJ16,"HCL")) | AU16: =IF($B16="","",COUNTIF($F16:$AJ16,"WO")) | AV16: =IF($B16="","",COUNTIF($F16:$AJ16,"PH")) | AW16: =IF($B16="","",COUNTIF($F16:$AJ16,"TR")) | AX16: =IF($B16="","",AO16+AS16/2) | AY16: =IF($B16="","",AQ16) | AZ16: =IF($B16="","",AP16+AT16/2) | BA16: =IF($B16="","",AK16+AN16+AM16/2+AO16+AP16+AQ16+AR16+AS16+AT16+AU16+AV16+AW16) | BB16: =IF($B16="","",MAX(0,AN16-Settings!$C$16)*Settings!$C$17) | BC16: =IF($B16="","",BA16-BB16) | BD16: =IF(OR($B16="",$A16=""),"",DAY(EOMONTH($A16,0))-COUNTA($F16:$AJ16))
C17: =IF($B17="","",IFERROR(INDEX(M_name,MATCH($B17,M_emp,0)),"Code not found")) | D17: =IF($B17="","",IFERROR(INDEX(M_dept,MATCH($B17,M_emp,0)),"")) | E17: =IF($B17="","",IFERROR(INDEX(M_loc,MATCH($B17,M_emp,0)),"")) | AK17: =IF($B17="","",COUNTIF($F17:$AJ17,"P")) | AL17: =IF($B17="","",COUNTIF($F17:$AJ17,"A")) | AM17: =IF($B17="","",COUNTIF($F17:$AJ17,"HA")) | AN17: =IF($B17="","",COUNTIF($F17:$AJ17,"L")) | AO17: =IF($B17="","",COUNTIF($F17:$AJ17,"PL")) | AP17: =IF($B17="","",COUNTIF($F17:$AJ17,"CL")) | AQ17: =IF($B17="","",COUNTIF($F17:$AJ17,"SL")) | AR17: =IF($B17="","",COUNTIF($F17:$AJ17,"CO")) | AS17: =IF($B17="","",COUNTIF($F17:$AJ17,"HPL")) | AT17: =IF($B17="","",COUNTIF($F17:$AJ17,"HCL")) | AU17: =IF($B17="","",COUNTIF($F17:$AJ17,"WO")) | AV17: =IF($B17="","",COUNTIF($F17:$AJ17,"PH")) | AW17: =IF($B17="","",COUNTIF($F17:$AJ17,"TR")) | AX17: =IF($B17="","",AO17+AS17/2) | AY17: =IF($B17="","",AQ17) | AZ17: =IF($B17="","",AP17+AT17/2) | BA17: =IF($B17="","",AK17+AN17+AM17/2+AO17+AP17+AQ17+AR17+AS17+AT17+AU17+AV17+AW17) | BB17: =IF($B17="","",MAX(0,AN17-Settings!$C$16)*Settings!$C$17) | BC17: =IF($B17="","",BA17-BB17) | BD17: =IF(OR($B17="",$A17=""),"",DAY(EOMONTH($A17,0))-COUNTA($F17:$AJ17))
... C2405: =IF($B2405="","",IFERROR(INDEX(M_name,MATCH($B2405,M_emp,0)),"Code not found")) | D2405: =IF($B2405="","",IFERROR(INDEX(M_dept,MATCH($B2405,M_emp,0)),"")) | E2405: =IF($B2405="","",IFERROR(INDEX(M_loc,MATCH($B2405,M_emp,0)),"")) | AK2405: =IF($B2405="","",COUNTIF($F2405:$AJ2405,"P")) | AL2405: =IF($B2405="","",COUNTIF($F2405:$AJ2405,"A")) | AM2405: =IF($B2405="","",COUNTIF($F2405:$AJ2405,"HA")) | AN2405: =IF($B2405="","",COUNTIF($F2405:$AJ2405,"L")) | AO2405: =IF($B2405="","",COUNTIF($F2405:$AJ2405,"PL")) | AP2405: =IF($B2405="","",COUNTIF($F2405:$AJ2405,"CL")) | AQ2405: =IF($B2405="","",COUNTIF($F2405:$AJ2405,"SL")) | AR2405: =IF($B2405="","",COUNTIF($F2405:$AJ2405,"CO")) | AS2405: =IF($B2405="","",COUNTIF($F2405:$AJ2405,"HPL")) | AT2405: =IF($B2405="","",COUNTIF($F2405:$AJ2405,"HCL")) | AU2405: =IF($B2405="","",COUNTIF($F2405:$AJ2405,"WO")) | AV2405: =IF($B2405="","",COUNTIF($F2405:$AJ2405,"PH")) | AW2405: =IF($B2405="","",COUNTIF($F2405:$AJ2405,"TR")) | AX2405: =IF($B2405="","",AO2405+AS2405/2) | AY2405: =IF($B2405="","",AQ2405) | AZ2405: =IF($B2405="","",AP2405+AT2405/2) | BA2405: =IF($B2405="","",AK2405+AN2405+AM2405/2+AO2405+AP2405+AQ2405+AR2405+AS2405+AT2405+AU2405+AV2405+AW2405) | BB2405: =IF($B2405="","",MAX(0,AN2405-Settings!$C$16)*Settings!$C$17) | BC2405: =IF($B2405="","",BA2405-BB2405) | BD2405: =IF(OR($B2405="",$A2405=""),"",DAY(EOMONTH($A2405,0))-COUNTA($F2405:$AJ2405))

Sheet Leave Record
A1: ="LEAVE RECORD - "&Settings!$C$5&" - Leave year "&LvYear -> LEAVE RECORD - Your Company Name - Leave year 2026
A2: How to use: employees appear automatically from the Employee List sheet. Only the yellow column (Carry Forward PL) is typed. Used leave is picked up from the Attendance sheet. Filter Status to see OVER-USED / LOW employees.
A5: Employee Code | B5: Employee Name | C5: Designation | D5: Department | E5: Location | F5: Status | G5: DOJ | H5: Confirmation Date | I5: Eligible From | J5: Leave Year End | K5: Eligible Days | L5: CL Entitled | M5: SL Entitled | N5: Carry Forward PL (INPUT) | O5: PL Full Year | P5: PL Accrued To Date | Q5: Training Days Allotted | R5: CL Used | S5: SL Used | T5: PL Used | U5: Training Used | V5: CL Pending | W5: SL Pending | X5: PL Pending | Y5: Training Pending | Z5: Total Leave Pending (CL+SL+PL) | AA5: PL Balance at Year End | AB5: Pending Summary | AC5: Status Flag | AD5: Alert #
A6: =IF('Employee List'!B6="","",'Employee List'!B6) | B6: =IF($A6="","",'Employee List'!C6) | C6: =IF($A6="","",'Employee List'!E6&"") | D6: =IF($A6="","",'Employee List'!F6&"") | E6: =IF($A6="","",'Employee List'!G6&"") | F6: =IF($A6="","",'Employee List'!D6) | G6: =IF($A6="","",IF('Employee List'!I6="","",'Employee List'!I6)) | H6: =IF(OR($A6="",G6=""),"",G6+Settings!$C$13) | I6: =IF(H6="","",MAX(H6,DATE(LvYear,1,1))) | J6: =IF($A6="","",IF('Employee List'!J6="",DATE(LvYear,12,31),MIN('Employee List'!J6,DATE(LvYear,12,31)))) | K6: =IF(OR(I6="",J6=""),"",MAX(0,J6-I6+1)) | L6: =IF($A6="","",IF(AND(ISNUMBER(K6),K6=0),0,Settings!$C$10)) | M6: =IF($A6="","",IF(AND(ISNUMBER(K6),K6=0),0,Settings!$C$11)) | O6: =IF($A6="","",FLOOR(Settings!$C$12/365*N(K6),0.5)) | P6: =IF($A6="","",IF(I6="",N(N6),FLOOR(Settings!$C$12/365*MAX(0,MIN(LvAsOf,J6)-I6+1)+N(N6),0.5))) | Q6: =IF($A6="","",Settings!$C$14) | R6: =IF($A6="","",SUMIFS(Attendance!$AZ$6:$AZ$2405,Attendance!$B$6:$B$2405,$A6,Attendance!$A$6:$A$2405,">="&DATE(LvYear,1,1),Attendance!$A$6:$A$2405,"<="&DATE(LvYear,12,31))) | S6: =IF($A6="","",SUMIFS(Attendance!$AY$6:$AY$2405,Attendance!$B$6:$B$2405,$A6,Attendance!$A$6:$A$2405,">="&DATE(LvYear,1,1),Attendance!$A$6:$A$2405,"<="&DATE(LvYear,12,31))) | T6: =IF($A6="","",SUMIFS(Attendance!$AX$6:$AX$2405,Attendance!$B$6:$B$2405,$A6,Attendance!$A$6:$A$2405,">="&DATE(LvYear,1,1),Attendance!$A$6:$A$2405,"<="&DATE(LvYear,12,31))) | U6: =IF($A6="","",SUMIFS(Attendance!$AW$6:$AW$2405,Attendance!$B$6:$B$2405,$A6,Attendance!$A$6:$A$2405,">="&DATE(LvYear,1,1),Attendance!$A$6:$A$2405,"<="&DATE(LvYear,12,31))) | V6: =IF($A6="","",L6-R6) | W6: =IF($A6="","",M6-S6) | X6: =IF($A6="","",P6-T6) | Y6: =IF($A6="","",Q6-U6) | Z6: =IF($A6="","",V6+W6+X6) | AA6: =IF($A6="","",O6+N(N6)-T6) | AB6: =IF($A6="","","CL "&V6&" | SL "&W6&" | PL "&X6&" | TR "&Y6) | AC6: =IF($A6="","",IF(F6="Exited","EXITED",IF(AND(ISNUMBER(K6),K6=0),"NOT ELIGIBLE",IF(MIN(V6:X6)<0,"OVER-USED",IF(Z6<=Settings!$C$15,"LOW","OK"))))) | AD6: =IF(OR(AC6="OVER-USED",AC6="LOW"),COUNTIF(AC$6:AC6,"OVER-USED")+COUNTIF(AC$6:AC6,"LOW"),"")
A7: =IF('Employee List'!B7="","",'Employee List'!B7) | B7: =IF($A7="","",'Employee List'!C7) | C7: =IF($A7="","",'Employee List'!E7&"") | D7: =IF($A7="","",'Employee List'!F7&"") | E7: =IF($A7="","",'Employee List'!G7&"") | F7: =IF($A7="","",'Employee List'!D7) | G7: =IF($A7="","",IF('Employee List'!I7="","",'Employee List'!I7)) | H7: =IF(OR($A7="",G7=""),"",G7+Settings!$C$13) | I7: =IF(H7="","",MAX(H7,DATE(LvYear,1,1))) | J7: =IF($A7="","",IF('Employee List'!J7="",DATE(LvYear,12,31),MIN('Employee List'!J7,DATE(LvYear,12,31)))) | K7: =IF(OR(I7="",J7=""),"",MAX(0,J7-I7+1)) | L7: =IF($A7="","",IF(AND(ISNUMBER(K7),K7=0),0,Settings!$C$10)) | M7: =IF($A7="","",IF(AND(ISNUMBER(K7),K7=0),0,Settings!$C$11)) | O7: =IF($A7="","",FLOOR(Settings!$C$12/365*N(K7),0.5)) | P7: =IF($A7="","",IF(I7="",N(N7),FLOOR(Settings!$C$12/365*MAX(0,MIN(LvAsOf,J7)-I7+1)+N(N7),0.5))) | Q7: =IF($A7="","",Settings!$C$14) | R7: =IF($A7="","",SUMIFS(Attendance!$AZ$6:$AZ$2405,Attendance!$B$6:$B$2405,$A7,Attendance!$A$6:$A$2405,">="&DATE(LvYear,1,1),Attendance!$A$6:$A$2405,"<="&DATE(LvYear,12,31))) | S7: =IF($A7="","",SUMIFS(Attendance!$AY$6:$AY$2405,Attendance!$B$6:$B$2405,$A7,Attendance!$A$6:$A$2405,">="&DATE(LvYear,1,1),Attendance!$A$6:$A$2405,"<="&DATE(LvYear,12,31))) | T7: =IF($A7="","",SUMIFS(Attendance!$AX$6:$AX$2405,Attendance!$B$6:$B$2405,$A7,Attendance!$A$6:$A$2405,">="&DATE(LvYear,1,1),Attendance!$A$6:$A$2405,"<="&DATE(LvYear,12,31))) | U7: =IF($A7="","",SUMIFS(Attendance!$AW$6:$AW$2405,Attendance!$B$6:$B$2405,$A7,Attendance!$A$6:$A$2405,">="&DATE(LvYear,1,1),Attendance!$A$6:$A$2405,"<="&DATE(LvYear,12,31))) | V7: =IF($A7="","",L7-R7) | W7: =IF($A7="","",M7-S7) | X7: =IF($A7="","",P7-T7) | Y7: =IF($A7="","",Q7-U7) | Z7: =IF($A7="","",V7+W7+X7) | AA7: =IF($A7="","",O7+N(N7)-T7) | AB7: =IF($A7="","","CL "&V7&" | SL "&W7&" | PL "&X7&" | TR "&Y7) | AC7: =IF($A7="","",IF(F7="Exited","EXITED",IF(AND(ISNUMBER(K7),K7=0),"NOT ELIGIBLE",IF(MIN(V7:X7)<0,"OVER-USED",IF(Z7<=Settings!$C$15,"LOW","OK"))))) | AD7: =IF(OR(AC7="OVER-USED",AC7="LOW"),COUNTIF(AC$6:AC7,"OVER-USED")+COUNTIF(AC$6:AC7,"LOW"),"")
A8: =IF('Employee List'!B8="","",'Employee List'!B8) | B8: =IF($A8="","",'Employee List'!C8) | C8: =IF($A8="","",'Employee List'!E8&"") | D8: =IF($A8="","",'Employee List'!F8&"") | E8: =IF($A8="","",'Employee List'!G8&"") | F8: =IF($A8="","",'Employee List'!D8) | G8: =IF($A8="","",IF('Employee List'!I8="","",'Employee List'!I8)) | H8: =IF(OR($A8="",G8=""),"",G8+Settings!$C$13) | I8: =IF(H8="","",MAX(H8,DATE(LvYear,1,1))) | J8: =IF($A8="","",IF('Employee List'!J8="",DATE(LvYear,12,31),MIN('Employee List'!J8,DATE(LvYear,12,31)))) | K8: =IF(OR(I8="",J8=""),"",MAX(0,J8-I8+1)) | L8: =IF($A8="","",IF(AND(ISNUMBER(K8),K8=0),0,Settings!$C$10)) | M8: =IF($A8="","",IF(AND(ISNUMBER(K8),K8=0),0,Settings!$C$11)) | O8: =IF($A8="","",FLOOR(Settings!$C$12/365*N(K8),0.5)) | P8: =IF($A8="","",IF(I8="",N(N8),FLOOR(Settings!$C$12/365*MAX(0,MIN(LvAsOf,J8)-I8+1)+N(N8),0.5))) | Q8: =IF($A8="","",Settings!$C$14) | R8: =IF($A8="","",SUMIFS(Attendance!$AZ$6:$AZ$2405,Attendance!$B$6:$B$2405,$A8,Attendance!$A$6:$A$2405,">="&DATE(LvYear,1,1),Attendance!$A$6:$A$2405,"<="&DATE(LvYear,12,31))) | S8: =IF($A8="","",SUMIFS(Attendance!$AY$6:$AY$2405,Attendance!$B$6:$B$2405,$A8,Attendance!$A$6:$A$2405,">="&DATE(LvYear,1,1),Attendance!$A$6:$A$2405,"<="&DATE(LvYear,12,31))) | T8: =IF($A8="","",SUMIFS(Attendance!$AX$6:$AX$2405,Attendance!$B$6:$B$2405,$A8,Attendance!$A$6:$A$2405,">="&DATE(LvYear,1,1),Attendance!$A$6:$A$2405,"<="&DATE(LvYear,12,31))) | U8: =IF($A8="","",SUMIFS(Attendance!$AW$6:$AW$2405,Attendance!$B$6:$B$2405,$A8,Attendance!$A$6:$A$2405,">="&DATE(LvYear,1,1),Attendance!$A$6:$A$2405,"<="&DATE(LvYear,12,31))) | V8: =IF($A8="","",L8-R8) | W8: =IF($A8="","",M8-S8) | X8: =IF($A8="","",P8-T8) | Y8: =IF($A8="","",Q8-U8) | Z8: =IF($A8="","",V8+W8+X8) | AA8: =IF($A8="","",O8+N(N8)-T8) | AB8: =IF($A8="","","CL "&V8&" | SL "&W8&" | PL "&X8&" | TR "&Y8) | AC8: =IF($A8="","",IF(F8="Exited","EXITED",IF(AND(ISNUMBER(K8),K8=0),"NOT ELIGIBLE",IF(MIN(V8:X8)<0,"OVER-USED",IF(Z8<=Settings!$C$15,"LOW","OK"))))) | AD8: =IF(OR(AC8="OVER-USED",AC8="LOW"),COUNTIF(AC$6:AC8,"OVER-USED")+COUNTIF(AC$6:AC8,"LOW"),"")
A9: =IF('Employee List'!B9="","",'Employee List'!B9) | B9: =IF($A9="","",'Employee List'!C9) | C9: =IF($A9="","",'Employee List'!E9&"") | D9: =IF($A9="","",'Employee List'!F9&"") | E9: =IF($A9="","",'Employee List'!G9&"") | F9: =IF($A9="","",'Employee List'!D9) | G9: =IF($A9="","",IF('Employee List'!I9="","",'Employee List'!I9)) | H9: =IF(OR($A9="",G9=""),"",G9+Settings!$C$13) | I9: =IF(H9="","",MAX(H9,DATE(LvYear,1,1))) | J9: =IF($A9="","",IF('Employee List'!J9="",DATE(LvYear,12,31),MIN('Employee List'!J9,DATE(LvYear,12,31)))) | K9: =IF(OR(I9="",J9=""),"",MAX(0,J9-I9+1)) | L9: =IF($A9="","",IF(AND(ISNUMBER(K9),K9=0),0,Settings!$C$10)) | M9: =IF($A9="","",IF(AND(ISNUMBER(K9),K9=0),0,Settings!$C$11)) | O9: =IF($A9="","",FLOOR(Settings!$C$12/365*N(K9),0.5)) | P9: =IF($A9="","",IF(I9="",N(N9),FLOOR(Settings!$C$12/365*MAX(0,MIN(LvAsOf,J9)-I9+1)+N(N9),0.5))) | Q9: =IF($A9="","",Settings!$C$14) | R9: =IF($A9="","",SUMIFS(Attendance!$AZ$6:$AZ$2405,Attendance!$B$6:$B$2405,$A9,Attendance!$A$6:$A$2405,">="&DATE(LvYear,1,1),Attendance!$A$6:$A$2405,"<="&DATE(LvYear,12,31))) | S9: =IF($A9="","",SUMIFS(Attendance!$AY$6:$AY$2405,Attendance!$B$6:$B$2405,$A9,Attendance!$A$6:$A$2405,">="&DATE(LvYear,1,1),Attendance!$A$6:$A$2405,"<="&DATE(LvYear,12,31))) | T9: =IF($A9="","",SUMIFS(Attendance!$AX$6:$AX$2405,Attendance!$B$6:$B$2405,$A9,Attendance!$A$6:$A$2405,">="&DATE(LvYear,1,1),Attendance!$A$6:$A$2405,"<="&DATE(LvYear,12,31))) | U9: =IF($A9="","",SUMIFS(Attendance!$AW$6:$AW$2405,Attendance!$B$6:$B$2405,$A9,Attendance!$A$6:$A$2405,">="&DATE(LvYear,1,1),Attendance!$A$6:$A$2405,"<="&DATE(LvYear,12,31))) | V9: =IF($A9="","",L9-R9) | W9: =IF($A9="","",M9-S9) | X9: =IF($A9="","",P9-T9) | Y9: =IF($A9="","",Q9-U9) | Z9: =IF($A9="","",V9+W9+X9) | AA9: =IF($A9="","",O9+N(N9)-T9) | AB9: =IF($A9="","","CL "&V9&" | SL "&W9&" | PL "&X9&" | TR "&Y9) | AC9: =IF($A9="","",IF(F9="Exited","EXITED",IF(AND(ISNUMBER(K9),K9=0),"NOT ELIGIBLE",IF(MIN(V9:X9)<0,"OVER-USED",IF(Z9<=Settings!$C$15,"LOW","OK"))))) | AD9: =IF(OR(AC9="OVER-USED",AC9="LOW"),COUNTIF(AC$6:AC9,"OVER-USED")+COUNTIF(AC$6:AC9,"LOW"),"")
A10: =IF('Employee List'!B10="","",'Employee List'!B10) | B10: =IF($A10="","",'Employee List'!C10) | C10: =IF($A10="","",'Employee List'!E10&"") | D10: =IF($A10="","",'Employee List'!F10&"") | E10: =IF($A10="","",'Employee List'!G10&"") | F10: =IF($A10="","",'Employee List'!D10) | G10: =IF($A10="","",IF('Employee List'!I10="","",'Employee List'!I10)) | H10: =IF(OR($A10="",G10=""),"",G10+Settings!$C$13) | I10: =IF(H10="","",MAX(H10,DATE(LvYear,1,1))) | J10: =IF($A10="","",IF('Employee List'!J10="",DATE(LvYear,12,31),MIN('Employee List'!J10,DATE(LvYear,12,31)))) | K10: =IF(OR(I10="",J10=""),"",MAX(0,J10-I10+1)) | L10: =IF($A10="","",IF(AND(ISNUMBER(K10),K10=0),0,Settings!$C$10)) | M10: =IF($A10="","",IF(AND(ISNUMBER(K10),K10=0),0,Settings!$C$11)) | O10: =IF($A10="","",FLOOR(Settings!$C$12/365*N(K10),0.5)) | P10: =IF($A10="","",IF(I10="",N(N10),FLOOR(Settings!$C$12/365*MAX(0,MIN(LvAsOf,J10)-I10+1)+N(N10),0.5))) | Q10: =IF($A10="","",Settings!$C$14) | R10: =IF($A10="","",SUMIFS(Attendance!$AZ$6:$AZ$2405,Attendance!$B$6:$B$2405,$A10,Attendance!$A$6:$A$2405,">="&DATE(LvYear,1,1),Attendance!$A$6:$A$2405,"<="&DATE(LvYear,12,31))) | S10: =IF($A10="","",SUMIFS(Attendance!$AY$6:$AY$2405,Attendance!$B$6:$B$2405,$A10,Attendance!$A$6:$A$2405,">="&DATE(LvYear,1,1),Attendance!$A$6:$A$2405,"<="&DATE(LvYear,12,31))) | T10: =IF($A10="","",SUMIFS(Attendance!$AX$6:$AX$2405,Attendance!$B$6:$B$2405,$A10,Attendance!$A$6:$A$2405,">="&DATE(LvYear,1,1),Attendance!$A$6:$A$2405,"<="&DATE(LvYear,12,31))) | U10: =IF($A10="","",SUMIFS(Attendance!$AW$6:$AW$2405,Attendance!$B$6:$B$2405,$A10,Attendance!$A$6:$A$2405,">="&DATE(LvYear,1,1),Attendance!$A$6:$A$2405,"<="&DATE(LvYear,12,31))) | V10: =IF($A10="","",L10-R10) | W10: =IF($A10="","",M10-S10) | X10: =IF($A10="","",P10-T10) | Y10: =IF($A10="","",Q10-U10) | Z10: =IF($A10="","",V10+W10+X10) | AA10: =IF($A10="","",O10+N(N10)-T10) | AB10: =IF($A10="","","CL "&V10&" | SL "&W10&" | PL "&X10&" | TR "&Y10) | AC10: =IF($A10="","",IF(F10="Exited","EXITED",IF(AND(ISNUMBER(K10),K10=0),"NOT ELIGIBLE",IF(MIN(V10:X10)<0,"OVER-USED",IF(Z10<=Settings!$C$15,"LOW","OK"))))) | AD10: =IF(OR(AC10="OVER-USED",AC10="LOW"),COUNTIF(AC$6:AC10,"OVER-USED")+COUNTIF(AC$6:AC10,"LOW"),"")
A11: =IF('Employee List'!B11="","",'Employee List'!B11) | B11: =IF($A11="","",'Employee List'!C11) | C11: =IF($A11="","",'Employee List'!E11&"") | D11: =IF($A11="","",'Employee List'!F11&"") | E11: =IF($A11="","",'Employee List'!G11&"") | F11: =IF($A11="","",'Employee List'!D11) | G11: =IF($A11="","",IF('Employee List'!I11="","",'Employee List'!I11)) | H11: =IF(OR($A11="",G11=""),"",G11+Settings!$C$13) | I11: =IF(H11="","",MAX(H11,DATE(LvYear,1,1))) | J11: =IF($A11="","",IF('Employee List'!J11="",DATE(LvYear,12,31),MIN('Employee List'!J11,DATE(LvYear,12,31)))) | K11: =IF(OR(I11="",J11=""),"",MAX(0,J11-I11+1)) | L11: =IF($A11="","",IF(AND(ISNUMBER(K11),K11=0),0,Settings!$C$10)) | M11: =IF($A11="","",IF(AND(ISNUMBER(K11),K11=0),0,Settings!$C$11)) | O11: =IF($A11="","",FLOOR(Settings!$C$12/365*N(K11),0.5)) | P11: =IF($A11="","",IF(I11="",N(N11),FLOOR(Settings!$C$12/365*MAX(0,MIN(LvAsOf,J11)-I11+1)+N(N11),0.5))) | Q11: =IF($A11="","",Settings!$C$14) | R11: =IF($A11="","",SUMIFS(Attendance!$AZ$6:$AZ$2405,Attendance!$B$6:$B$2405,$A11,Attendance!$A$6:$A$2405,">="&DATE(LvYear,1,1),Attendance!$A$6:$A$2405,"<="&DATE(LvYear,12,31))) | S11: =IF($A11="","",SUMIFS(Attendance!$AY$6:$AY$2405,Attendance!$B$6:$B$2405,$A11,Attendance!$A$6:$A$2405,">="&DATE(LvYear,1,1),Attendance!$A$6:$A$2405,"<="&DATE(LvYear,12,31))) | T11: =IF($A11="","",SUMIFS(Attendance!$AX$6:$AX$2405,Attendance!$B$6:$B$2405,$A11,Attendance!$A$6:$A$2405,">="&DATE(LvYear,1,1),Attendance!$A$6:$A$2405,"<="&DATE(LvYear,12,31))) | U11: =IF($A11="","",SUMIFS(Attendance!$AW$6:$AW$2405,Attendance!$B$6:$B$2405,$A11,Attendance!$A$6:$A$2405,">="&DATE(LvYear,1,1),Attendance!$A$6:$A$2405,"<="&DATE(LvYear,12,31))) | V11: =IF($A11="","",L11-R11) | W11: =IF($A11="","",M11-S11) | X11: =IF($A11="","",P11-T11) | Y11: =IF($A11="","",Q11-U11) | Z11: =IF($A11="","",V11+W11+X11) | AA11: =IF($A11="","",O11+N(N11)-T11) | AB11: =IF($A11="","","CL "&V11&" | SL "&W11&" | PL "&X11&" | TR "&Y11) | AC11: =IF($A11="","",IF(F11="Exited","EXITED",IF(AND(ISNUMBER(K11),K11=0),"NOT ELIGIBLE",IF(MIN(V11:X11)<0,"OVER-USED",IF(Z11<=Settings!$C$15,"LOW","OK"))))) | AD11: =IF(OR(AC11="OVER-USED",AC11="LOW"),COUNTIF(AC$6:AC11,"OVER-USED")+COUNTIF(AC$6:AC11,"LOW"),"")
A12: =IF('Employee List'!B12="","",'Employee List'!B12) | B12: =IF($A12="","",'Employee List'!C12) | C12: =IF($A12="","",'Employee List'!E12&"") | D12: =IF($A12="","",'Employee List'!F12&"") | E12: =IF($A12="","",'Employee List'!G12&"") | F12: =IF($A12="","",'Employee List'!D12) | G12: =IF($A12="","",IF('Employee List'!I12="","",'Employee List'!I12)) | H12: =IF(OR($A12="",G12=""),"",G12+Settings!$C$13) | I12: =IF(H12="","",MAX(H12,DATE(LvYear,1,1))) | J12: =IF($A12="","",IF('Employee List'!J12="",DATE(LvYear,12,31),MIN('Employee List'!J12,DATE(LvYear,12,31)))) | K12: =IF(OR(I12="",J12=""),"",MAX(0,J12-I12+1)) | L12: =IF($A12="","",IF(AND(ISNUMBER(K12),K12=0),0,Settings!$C$10)) | M12: =IF($A12="","",IF(AND(ISNUMBER(K12),K12=0),0,Settings!$C$11)) | O12: =IF($A12="","",FLOOR(Settings!$C$12/365*N(K12),0.5)) | P12: =IF($A12="","",IF(I12="",N(N12),FLOOR(Settings!$C$12/365*MAX(0,MIN(LvAsOf,J12)-I12+1)+N(N12),0.5))) | Q12: =IF($A12="","",Settings!$C$14) | R12: =IF($A12="","",SUMIFS(Attendance!$AZ$6:$AZ$2405,Attendance!$B$6:$B$2405,$A12,Attendance!$A$6:$A$2405,">="&DATE(LvYear,1,1),Attendance!$A$6:$A$2405,"<="&DATE(LvYear,12,31))) | S12: =IF($A12="","",SUMIFS(Attendance!$AY$6:$AY$2405,Attendance!$B$6:$B$2405,$A12,Attendance!$A$6:$A$2405,">="&DATE(LvYear,1,1),Attendance!$A$6:$A$2405,"<="&DATE(LvYear,12,31))) | T12: =IF($A12="","",SUMIFS(Attendance!$AX$6:$AX$2405,Attendance!$B$6:$B$2405,$A12,Attendance!$A$6:$A$2405,">="&DATE(LvYear,1,1),Attendance!$A$6:$A$2405,"<="&DATE(LvYear,12,31))) | U12: =IF($A12="","",SUMIFS(Attendance!$AW$6:$AW$2405,Attendance!$B$6:$B$2405,$A12,Attendance!$A$6:$A$2405,">="&DATE(LvYear,1,1),Attendance!$A$6:$A$2405,"<="&DATE(LvYear,12,31))) | V12: =IF($A12="","",L12-R12) | W12: =IF($A12="","",M12-S12) | X12: =IF($A12="","",P12-T12) | Y12: =IF($A12="","",Q12-U12) | Z12: =IF($A12="","",V12+W12+X12) | AA12: =IF($A12="","",O12+N(N12)-T12) | AB12: =IF($A12="","","CL "&V12&" | SL "&W12&" | PL "&X12&" | TR "&Y12) | AC12: =IF($A12="","",IF(F12="Exited","EXITED",IF(AND(ISNUMBER(K12),K12=0),"NOT ELIGIBLE",IF(MIN(V12:X12)<0,"OVER-USED",IF(Z12<=Settings!$C$15,"LOW","OK"))))) | AD12: =IF(OR(AC12="OVER-USED",AC12="LOW"),COUNTIF(AC$6:AC12,"OVER-USED")+COUNTIF(AC$6:AC12,"LOW"),"")
A13: =IF('Employee List'!B13="","",'Employee List'!B13) | B13: =IF($A13="","",'Employee List'!C13) | C13: =IF($A13="","",'Employee List'!E13&"") | D13: =IF($A13="","",'Employee List'!F13&"") | E13: =IF($A13="","",'Employee List'!G13&"") | F13: =IF($A13="","",'Employee List'!D13) | G13: =IF($A13="","",IF('Employee List'!I13="","",'Employee List'!I13)) | H13: =IF(OR($A13="",G13=""),"",G13+Settings!$C$13) | I13: =IF(H13="","",MAX(H13,DATE(LvYear,1,1))) | J13: =IF($A13="","",IF('Employee List'!J13="",DATE(LvYear,12,31),MIN('Employee List'!J13,DATE(LvYear,12,31)))) | K13: =IF(OR(I13="",J13=""),"",MAX(0,J13-I13+1)) | L13: =IF($A13="","",IF(AND(ISNUMBER(K13),K13=0),0,Settings!$C$10)) | M13: =IF($A13="","",IF(AND(ISNUMBER(K13),K13=0),0,Settings!$C$11)) | O13: =IF($A13="","",FLOOR(Settings!$C$12/365*N(K13),0.5)) | P13: =IF($A13="","",IF(I13="",N(N13),FLOOR(Settings!$C$12/365*MAX(0,MIN(LvAsOf,J13)-I13+1)+N(N13),0.5))) | Q13: =IF($A13="","",Settings!$C$14) | R13: =IF($A13="","",SUMIFS(Attendance!$AZ$6:$AZ$2405,Attendance!$B$6:$B$2405,$A13,Attendance!$A$6:$A$2405,">="&DATE(LvYear,1,1),Attendance!$A$6:$A$2405,"<="&DATE(LvYear,12,31))) | S13: =IF($A13="","",SUMIFS(Attendance!$AY$6:$AY$2405,Attendance!$B$6:$B$2405,$A13,Attendance!$A$6:$A$2405,">="&DATE(LvYear,1,1),Attendance!$A$6:$A$2405,"<="&DATE(LvYear,12,31))) | T13: =IF($A13="","",SUMIFS(Attendance!$AX$6:$AX$2405,Attendance!$B$6:$B$2405,$A13,Attendance!$A$6:$A$2405,">="&DATE(LvYear,1,1),Attendance!$A$6:$A$2405,"<="&DATE(LvYear,12,31))) | U13: =IF($A13="","",SUMIFS(Attendance!$AW$6:$AW$2405,Attendance!$B$6:$B$2405,$A13,Attendance!$A$6:$A$2405,">="&DATE(LvYear,1,1),Attendance!$A$6:$A$2405,"<="&DATE(LvYear,12,31))) | V13: =IF($A13="","",L13-R13) | W13: =IF($A13="","",M13-S13) | X13: =IF($A13="","",P13-T13) | Y13: =IF($A13="","",Q13-U13) | Z13: =IF($A13="","",V13+W13+X13) | AA13: =IF($A13="","",O13+N(N13)-T13) | AB13: =IF($A13="","","CL "&V13&" | SL "&W13&" | PL "&X13&" | TR "&Y13) | AC13: =IF($A13="","",IF(F13="Exited","EXITED",IF(AND(ISNUMBER(K13),K13=0),"NOT ELIGIBLE",IF(MIN(V13:X13)<0,"OVER-USED",IF(Z13<=Settings!$C$15,"LOW","OK"))))) | AD13: =IF(OR(AC13="OVER-USED",AC13="LOW"),COUNTIF(AC$6:AC13,"OVER-USED")+COUNTIF(AC$6:AC13,"LOW"),"")
A14: =IF('Employee List'!B14="","",'Employee List'!B14) | B14: =IF($A14="","",'Employee List'!C14) | C14: =IF($A14="","",'Employee List'!E14&"") | D14: =IF($A14="","",'Employee List'!F14&"") | E14: =IF($A14="","",'Employee List'!G14&"") | F14: =IF($A14="","",'Employee List'!D14) | G14: =IF($A14="","",IF('Employee List'!I14="","",'Employee List'!I14)) | H14: =IF(OR($A14="",G14=""),"",G14+Settings!$C$13) | I14: =IF(H14="","",MAX(H14,DATE(LvYear,1,1))) | J14: =IF($A14="","",IF('Employee List'!J14="",DATE(LvYear,12,31),MIN('Employee List'!J14,DATE(LvYear,12,31)))) | K14: =IF(OR(I14="",J14=""),"",MAX(0,J14-I14+1)) | L14: =IF($A14="","",IF(AND(ISNUMBER(K14),K14=0),0,Settings!$C$10)) | M14: =IF($A14="","",IF(AND(ISNUMBER(K14),K14=0),0,Settings!$C$11)) | O14: =IF($A14="","",FLOOR(Settings!$C$12/365*N(K14),0.5)) | P14: =IF($A14="","",IF(I14="",N(N14),FLOOR(Settings!$C$12/365*MAX(0,MIN(LvAsOf,J14)-I14+1)+N(N14),0.5))) | Q14: =IF($A14="","",Settings!$C$14) | R14: =IF($A14="","",SUMIFS(Attendance!$AZ$6:$AZ$2405,Attendance!$B$6:$B$2405,$A14,Attendance!$A$6:$A$2405,">="&DATE(LvYear,1,1),Attendance!$A$6:$A$2405,"<="&DATE(LvYear,12,31))) | S14: =IF($A14="","",SUMIFS(Attendance!$AY$6:$AY$2405,Attendance!$B$6:$B$2405,$A14,Attendance!$A$6:$A$2405,">="&DATE(LvYear,1,1),Attendance!$A$6:$A$2405,"<="&DATE(LvYear,12,31))) | T14: =IF($A14="","",SUMIFS(Attendance!$AX$6:$AX$2405,Attendance!$B$6:$B$2405,$A14,Attendance!$A$6:$A$2405,">="&DATE(LvYear,1,1),Attendance!$A$6:$A$2405,"<="&DATE(LvYear,12,31))) | U14: =IF($A14="","",SUMIFS(Attendance!$AW$6:$AW$2405,Attendance!$B$6:$B$2405,$A14,Attendance!$A$6:$A$2405,">="&DATE(LvYear,1,1),Attendance!$A$6:$A$2405,"<="&DATE(LvYear,12,31))) | V14: =IF($A14="","",L14-R14) | W14: =IF($A14="","",M14-S14) | X14: =IF($A14="","",P14-T14) | Y14: =IF($A14="","",Q14-U14) | Z14: =IF($A14="","",V14+W14+X14) | AA14: =IF($A14="","",O14+N(N14)-T14) | AB14: =IF($A14="","","CL "&V14&" | SL "&W14&" | PL "&X14&" | TR "&Y14) | AC14: =IF($A14="","",IF(F14="Exited","EXITED",IF(AND(ISNUMBER(K14),K14=0),"NOT ELIGIBLE",IF(MIN(V14:X14)<0,"OVER-USED",IF(Z14<=Settings!$C$15,"LOW","OK"))))) | AD14: =IF(OR(AC14="OVER-USED",AC14="LOW"),COUNTIF(AC$6:AC14,"OVER-USED")+COUNTIF(AC$6:AC14,"LOW"),"")
A15: =IF('Employee List'!B15="","",'Employee List'!B15) | B15: =IF($A15="","",'Employee List'!C15) | C15: =IF($A15="","",'Employee List'!E15&"") | D15: =IF($A15="","",'Employee List'!F15&"") | E15: =IF($A15="","",'Employee List'!G15&"") | F15: =IF($A15="","",'Employee List'!D15) | G15: =IF($A15="","",IF('Employee List'!I15="","",'Employee List'!I15)) | H15: =IF(OR($A15="",G15=""),"",G15+Settings!$C$13) | I15: =IF(H15="","",MAX(H15,DATE(LvYear,1,1))) | J15: =IF($A15="","",IF('Employee List'!J15="",DATE(LvYear,12,31),MIN('Employee List'!J15,DATE(LvYear,12,31)))) | K15: =IF(OR(I15="",J15=""),"",MAX(0,J15-I15+1)) | L15: =IF($A15="","",IF(AND(ISNUMBER(K15),K15=0),0,Settings!$C$10)) | M15: =IF($A15="","",IF(AND(ISNUMBER(K15),K15=0),0,Settings!$C$11)) | O15: =IF($A15="","",FLOOR(Settings!$C$12/365*N(K15),0.5)) | P15: =IF($A15="","",IF(I15="",N(N15),FLOOR(Settings!$C$12/365*MAX(0,MIN(LvAsOf,J15)-I15+1)+N(N15),0.5))) | Q15: =IF($A15="","",Settings!$C$14) | R15: =IF($A15="","",SUMIFS(Attendance!$AZ$6:$AZ$2405,Attendance!$B$6:$B$2405,$A15,Attendance!$A$6:$A$2405,">="&DATE(LvYear,1,1),Attendance!$A$6:$A$2405,"<="&DATE(LvYear,12,31))) | S15: =IF($A15="","",SUMIFS(Attendance!$AY$6:$AY$2405,Attendance!$B$6:$B$2405,$A15,Attendance!$A$6:$A$2405,">="&DATE(LvYear,1,1),Attendance!$A$6:$A$2405,"<="&DATE(LvYear,12,31))) | T15: =IF($A15="","",SUMIFS(Attendance!$AX$6:$AX$2405,Attendance!$B$6:$B$2405,$A15,Attendance!$A$6:$A$2405,">="&DATE(LvYear,1,1),Attendance!$A$6:$A$2405,"<="&DATE(LvYear,12,31))) | U15: =IF($A15="","",SUMIFS(Attendance!$AW$6:$AW$2405,Attendance!$B$6:$B$2405,$A15,Attendance!$A$6:$A$2405,">="&DATE(LvYear,1,1),Attendance!$A$6:$A$2405,"<="&DATE(LvYear,12,31))) | V15: =IF($A15="","",L15-R15) | W15: =IF($A15="","",M15-S15) | X15: =IF($A15="","",P15-T15) | Y15: =IF($A15="","",Q15-U15) | Z15: =IF($A15="","",V15+W15+X15) | AA15: =IF($A15="","",O15+N(N15)-T15) | AB15: =IF($A15="","","CL "&V15&" | SL "&W15&" | PL "&X15&" | TR "&Y15) | AC15: =IF($A15="","",IF(F15="Exited","EXITED",IF(AND(ISNUMBER(K15),K15=0),"NOT ELIGIBLE",IF(MIN(V15:X15)<0,"OVER-USED",IF(Z15<=Settings!$C$15,"LOW","OK"))))) | AD15: =IF(OR(AC15="OVER-USED",AC15="LOW"),COUNTIF(AC$6:AC15,"OVER-USED")+COUNTIF(AC$6:AC15,"LOW"),"")
A16: =IF('Employee List'!B16="","",'Employee List'!B16) | B16: =IF($A16="","",'Employee List'!C16) | C16: =IF($A16="","",'Employee List'!E16&"") | D16: =IF($A16="","",'Employee List'!F16&"") | E16: =IF($A16="","",'Employee List'!G16&"") | F16: =IF($A16="","",'Employee List'!D16) | G16: =IF($A16="","",IF('Employee List'!I16="","",'Employee List'!I16)) | H16: =IF(OR($A16="",G16=""),"",G16+Settings!$C$13) | I16: =IF(H16="","",MAX(H16,DATE(LvYear,1,1))) | J16: =IF($A16="","",IF('Employee List'!J16="",DATE(LvYear,12,31),MIN('Employee List'!J16,DATE(LvYear,12,31)))) | K16: =IF(OR(I16="",J16=""),"",MAX(0,J16-I16+1)) | L16: =IF($A16="","",IF(AND(ISNUMBER(K16),K16=0),0,Settings!$C$10)) | M16: =IF($A16="","",IF(AND(ISNUMBER(K16),K16=0),0,Settings!$C$11)) | O16: =IF($A16="","",FLOOR(Settings!$C$12/365*N(K16),0.5)) | P16: =IF($A16="","",IF(I16="",N(N16),FLOOR(Settings!$C$12/365*MAX(0,MIN(LvAsOf,J16)-I16+1)+N(N16),0.5))) | Q16: =IF($A16="","",Settings!$C$14) | R16: =IF($A16="","",SUMIFS(Attendance!$AZ$6:$AZ$2405,Attendance!$B$6:$B$2405,$A16,Attendance!$A$6:$A$2405,">="&DATE(LvYear,1,1),Attendance!$A$6:$A$2405,"<="&DATE(LvYear,12,31))) | S16: =IF($A16="","",SUMIFS(Attendance!$AY$6:$AY$2405,Attendance!$B$6:$B$2405,$A16,Attendance!$A$6:$A$2405,">="&DATE(LvYear,1,1),Attendance!$A$6:$A$2405,"<="&DATE(LvYear,12,31))) | T16: =IF($A16="","",SUMIFS(Attendance!$AX$6:$AX$2405,Attendance!$B$6:$B$2405,$A16,Attendance!$A$6:$A$2405,">="&DATE(LvYear,1,1),Attendance!$A$6:$A$2405,"<="&DATE(LvYear,12,31))) | U16: =IF($A16="","",SUMIFS(Attendance!$AW$6:$AW$2405,Attendance!$B$6:$B$2405,$A16,Attendance!$A$6:$A$2405,">="&DATE(LvYear,1,1),Attendance!$A$6:$A$2405,"<="&DATE(LvYear,12,31))) | V16: =IF($A16="","",L16-R16) | W16: =IF($A16="","",M16-S16) | X16: =IF($A16="","",P16-T16) | Y16: =IF($A16="","",Q16-U16) | Z16: =IF($A16="","",V16+W16+X16) | AA16: =IF($A16="","",O16+N(N16)-T16) | AB16: =IF($A16="","","CL "&V16&" | SL "&W16&" | PL "&X16&" | TR "&Y16) | AC16: =IF($A16="","",IF(F16="Exited","EXITED",IF(AND(ISNUMBER(K16),K16=0),"NOT ELIGIBLE",IF(MIN(V16:X16)<0,"OVER-USED",IF(Z16<=Settings!$C$15,"LOW","OK"))))) | AD16: =IF(OR(AC16="OVER-USED",AC16="LOW"),COUNTIF(AC$6:AC16,"OVER-USED")+COUNTIF(AC$6:AC16,"LOW"),"")
A17: =IF('Employee List'!B17="","",'Employee List'!B17) | B17: =IF($A17="","",'Employee List'!C17) | C17: =IF($A17="","",'Employee List'!E17&"") | D17: =IF($A17="","",'Employee List'!F17&"") | E17: =IF($A17="","",'Employee List'!G17&"") | F17: =IF($A17="","",'Employee List'!D17) | G17: =IF($A17="","",IF('Employee List'!I17="","",'Employee List'!I17)) | H17: =IF(OR($A17="",G17=""),"",G17+Settings!$C$13) | I17: =IF(H17="","",MAX(H17,DATE(LvYear,1,1))) | J17: =IF($A17="","",IF('Employee List'!J17="",DATE(LvYear,12,31),MIN('Employee List'!J17,DATE(LvYear,12,31)))) | K17: =IF(OR(I17="",J17=""),"",MAX(0,J17-I17+1)) | L17: =IF($A17="","",IF(AND(ISNUMBER(K17),K17=0),0,Settings!$C$10)) | M17: =IF($A17="","",IF(AND(ISNUMBER(K17),K17=0),0,Settings!$C$11)) | O17: =IF($A17="","",FLOOR(Settings!$C$12/365*N(K17),0.5)) | P17: =IF($A17="","",IF(I17="",N(N17),FLOOR(Settings!$C$12/365*MAX(0,MIN(LvAsOf,J17)-I17+1)+N(N17),0.5))) | Q17: =IF($A17="","",Settings!$C$14) | R17: =IF($A17="","",SUMIFS(Attendance!$AZ$6:$AZ$2405,Attendance!$B$6:$B$2405,$A17,Attendance!$A$6:$A$2405,">="&DATE(LvYear,1,1),Attendance!$A$6:$A$2405,"<="&DATE(LvYear,12,31))) | S17: =IF($A17="","",SUMIFS(Attendance!$AY$6:$AY$2405,Attendance!$B$6:$B$2405,$A17,Attendance!$A$6:$A$2405,">="&DATE(LvYear,1,1),Attendance!$A$6:$A$2405,"<="&DATE(LvYear,12,31))) | T17: =IF($A17="","",SUMIFS(Attendance!$AX$6:$AX$2405,Attendance!$B$6:$B$2405,$A17,Attendance!$A$6:$A$2405,">="&DATE(LvYear,1,1),Attendance!$A$6:$A$2405,"<="&DATE(LvYear,12,31))) | U17: =IF($A17="","",SUMIFS(Attendance!$AW$6:$AW$2405,Attendance!$B$6:$B$2405,$A17,Attendance!$A$6:$A$2405,">="&DATE(LvYear,1,1),Attendance!$A$6:$A$2405,"<="&DATE(LvYear,12,31))) | V17: =IF($A17="","",L17-R17) | W17: =IF($A17="","",M17-S17) | X17: =IF($A17="","",P17-T17) | Y17: =IF($A17="","",Q17-U17) | Z17: =IF($A17="","",V17+W17+X17) | AA17: =IF($A17="","",O17+N(N17)-T17) | AB17: =IF($A17="","","CL "&V17&" | SL "&W17&" | PL "&X17&" | TR "&Y17) | AC17: =IF($A17="","",IF(F17="Exited","EXITED",IF(AND(ISNUMBER(K17),K17=0),"NOT ELIGIBLE",IF(MIN(V17:X17)<0,"OVER-USED",IF(Z17<=Settings!$C$15,"LOW","OK"))))) | AD17: =IF(OR(AC17="OVER-USED",AC17="LOW"),COUNTIF(AC$6:AC17,"OVER-USED")+COUNTIF(AC$6:AC17,"LOW"),"")
... A505: =IF('Employee List'!B505="","",'Employee List'!B505) | B505: =IF($A505="","",'Employee List'!C505) | C505: =IF($A505="","",'Employee List'!E505&"") | D505: =IF($A505="","",'Employee List'!F505&"") | E505: =IF($A505="","",'Employee List'!G505&"") | F505: =IF($A505="","",'Employee List'!D505) | G505: =IF($A505="","",IF('Employee List'!I505="","",'Employee List'!I505)) | H505: =IF(OR($A505="",G505=""),"",G505+Settings!$C$13) | I505: =IF(H505="","",MAX(H505,DATE(LvYear,1,1))) | J505: =IF($A505="","",IF('Employee List'!J505="",DATE(LvYear,12,31),MIN('Employee List'!J505,DATE(LvYear,12,31)))) | K505: =IF(OR(I505="",J505=""),"",MAX(0,J505-I505+1)) | L505: =IF($A505="","",IF(AND(ISNUMBER(K505),K505=0),0,Settings!$C$10)) | M505: =IF($A505="","",IF(AND(ISNUMBER(K505),K505=0),0,Settings!$C$11)) | O505: =IF($A505="","",FLOOR(Settings!$C$12/365*N(K505),0.5)) | P505: =IF($A505="","",IF(I505="",N(N505),FLOOR(Settings!$C$12/365*MAX(0,MIN(LvAsOf,J505)-I505+1)+N(N505),0.5))) | Q505: =IF($A505="","",Settings!$C$14) | R505: =IF($A505="","",SUMIFS(Attendance!$AZ$6:$AZ$2405,Attendance!$B$6:$B$2405,$A505,Attendance!$A$6:$A$2405,">="&DATE(LvYear,1,1),Attendance!$A$6:$A$2405,"<="&DATE(LvYear,12,31))) | S505: =IF($A505="","",SUMIFS(Attendance!$AY$6:$AY$2405,Attendance!$B$6:$B$2405,$A505,Attendance!$A$6:$A$2405,">="&DATE(LvYear,1,1),Attendance!$A$6:$A$2405,"<="&DATE(LvYear,12,31))) | T505: =IF($A505="","",SUMIFS(Attendance!$AX$6:$AX$2405,Attendance!$B$6:$B$2405,$A505,Attendance!$A$6:$A$2405,">="&DATE(LvYear,1,1),Attendance!$A$6:$A$2405,"<="&DATE(LvYear,12,31))) | U505: =IF($A505="","",SUMIFS(Attendance!$AW$6:$AW$2405,Attendance!$B$6:$B$2405,$A505,Attendance!$A$6:$A$2405,">="&DATE(LvYear,1,1),Attendance!$A$6:$A$2405,"<="&DATE(LvYear,12,31))) | V505: =IF($A505="","",L505-R505) | W505: =IF($A505="","",M505-S505) | X505: =IF($A505="","",P505-T505) | Y505: =IF($A505="","",Q505-U505) | Z505: =IF($A505="","",V505+W505+X505) | AA505: =IF($A505="","",O505+N(N505)-T505) | AB505: =IF($A505="","","CL "&V505&" | SL "&W505&" | PL "&X505&" | TR "&Y505) | AC505: =IF($A505="","",IF(F505="Exited","EXITED",IF(AND(ISNUMBER(K505),K505=0),"NOT ELIGIBLE",IF(MIN(V505:X505)<0,"OVER-USED",IF(Z505<=Settings!$C$15,"LOW","OK"))))) | AD505: =IF(OR(AC505="OVER-USED",AC505="LOW"),COUNTIF(AC$6:AC505,"OVER-USED")+COUNTIF(AC$6:AC505,"LOW"),"")

Sheet Settings
B1: Settings & Legend
B2: Yellow cells with blue text are inputs - edit them and every sheet recalculates.
B4: Setting | C4: Value | D4: Note
B5: Company name | C5: Your Company Name | D5: Appears in the titles of every sheet.
B6: Report / As-of date | C6: =TODAY() -> 46322 | D6: Auto = today. Type a fixed date to freeze age / tenure / birthday calculations.
B7: Leave year | C7: =YEAR(C6) -> 2026 | D7: Auto = year of the report date. Type a year (e.g. 2026) to fix it. Carry-forward PL is entered in Leave Record.
B8: Current financial year (auto) | C8: =IF(MONTH(C6)>=4,YEAR(C6),YEAR(C6)-1)&"-"&RIGHT(IF(MONTH(C6)>=4,YEAR(C6),YEAR(C6)-1)+1,2) -> 2026-27 | D8: Apr-Mar. Used for joiners / exits this FY.
B9: Leave as-of date (auto) | C9: =MIN(C6,DATE(C7,12,31)) -> 46322 | D9: Report date capped at the leave-year end.
B10: CL (Casual Leave) per year | C10: 7 | D10: Default from your Leave Tracker template.
B11: SL (Sick Leave) per year | C11: 7 | D11: Default from your Leave Tracker template.
B12: PL (Paid Leave) per year | C12: 18 | D12: Accrued pro-rata: PL/365 per day from the eligibility date (rounded down to 0.5).
B13: Confirmation period (days after DOJ) | C13: 90 | D13: Leave starts after confirmation (DOJ + this many days).
B14: Training days per year (per employee) | C14: 0 | D14: ASSUMPTION: set to your training policy (0 = none).
B15: "LOW" alert when total pending (CL+SL+PL) is at or below | C15: 3 | D15: Flags employees on the Dashboard attention list.
B16: Free late marks per month before deduction | C16: 3 | D16: Default from your Leave Tracker template.
B17: Deduction per extra late mark (days) | C17: 0.5 | D17: Default from your Leave Tracker template.
B18: Birthday / anniversary alert window (days) | C18: 30 | D18: Dashboard counts birthdays and work anniversaries within this many days.
B21: Attendance codes (type or pick from the dropdown in the day cells of the Attendance sheet)
B22: Code | C22: Meaning | D22: Effect on payable days / leave balance
B23: P | C23: Present | D23: 1 payable day
B24: A | C24: Absent | D24: Not paid
B25: HA | C25: Half-day absent | D25: 0.5 payable day
B26: L | C26: Late | D26: 1 payable day; counts toward late deduction
B27: PL | C27: Paid Leave | D27: 1 payable day; 1 deducted from PL balance
B28: HPL | C28: Half-day Paid Leave | D28: 1 payable day (0.5 leave + 0.5 worked); 0.5 deducted from PL balance
B29: CL | C29: Casual Leave | D29: 1 payable day; 1 deducted from CL balance
B30: HCL | C30: Half-day Casual Leave | D30: 1 payable day (0.5 leave + 0.5 worked); 0.5 deducted from CL balance
B31: SL | C31: Sick Leave | D31: 1 payable day; 1 deducted from SL balance
B32: CO | C32: Compensatory Off | D32: 1 payable day
B33: WO | C33: Weekly Off | D33: 1 payable day
... B35: TR | C35: Training Day | D35: 1 payable day; counted against Training days balance
B37: Note: half-day codes (HA, HPL, HCL) are treated as shown above. If your payroll rule is different, edit the Gross Payable Days formula in Attendance column BA.

Sheet Lists
A1: Lists (dropdown options)
A2: Overwrite the example Departments, Locations and Designations with your own. Type new options under the last item of a list. Do not delete the header row.
A4: Department | B4: Location | C4: Designation
A5: Admin | B5: Location 1 | C5: Manager
A6: Accounts | B6: Location 2 | C6: Executive
A7: HR | C7: Supervisor
A8: IT | C8: Operator
A9: Operations | C9: Assistant
A10: Production
A11: Sales
A12: Stores
